[[{"complexity": 2, "task": 0, "trial": 1, "no._explored_programs": 773, "best_cost_per_iteration": [[0, 5], [0, 3], [1, 1], [2, 0]], "no._iterations": 3, "execution_time": 0.0202639, "best_program": "Program([[MoveUp], [Grab, MoveDown], [Drop, MoveUp]])", "test_cost": 0, "test_correct": 1, "train_cost": 0, "train_correct": 1, "test_total": 1, "prune_count": 470}, {"complexity": 2, "task": 1, "trial": 1, "no._explored_programs": 1060, "best_cost_per_iteration": [[0, 6], [0, 4], [1, 2], [2, 1], [4, 0]], "no._iterations": 5, "execution_time": 0.03293471799999999, "best_program": "Program([[MoveLeft], [Grab, MoveRight], [Drop, MoveLeft], [MoveDown]])", "test_cost": 0, "test_correct": 1, "train_cost": 0, "train_correct": 1, "test_total": 1, "prune_count": 951}, {"complexity": 2, "task": 2, "trial": 1, "no._explored_programs": 1043, "best_cost_per_iteration": [[0, 6], [0, 4], [1, 2], [2, 1], [3, 0]], "no._iterations": 4, "execution_time": 0.028452895000000006, "best_program": "Program([[MoveUp], [Grab, MoveLeft], [Drop, MoveRight], [MoveDown]])", "test_cost": 0, "test_correct": 1, "train_cost": 0, "train_correct": 1, "test_total": 1, "prune_count": 584}, {"complexity": 2, "task": 3, "trial": 1, "no._explored_programs": 682, "best_cost_per_iteration": [[0, 6], [0, 5], [0, 3], [1, 1], [2, 0]], "no._iterations": 3, "execution_time": 0.01984182999999999, "best_program": "Program([[MoveUp, MoveRight], [Grab, MoveDown], [Drop, MoveLeft]])", "test_cost": 0, "test_correct": 1, "train_cost": 0, "train_correct": 1, "test_total": 1, "prune_count": 561}, {"complexity": 2, "task": 4, "trial": 1, "no._explored_programs": 854, "best_cost_per_iteration": [[0, 4], [0, 2], [1, 1], [2, 0]], "no._iterations": 3, "execution_time": 0.022772365000000003, "best_program": "Program([[Grab, MoveUp], [Drop, MoveRight], [MoveDown]])", "test_cost": 0, "test_correct": 1, "train_cost": 0, "train_correct": 1, "test_total": 1, "prune_count": 389}, {"complexity": 2, "task": 5, "trial": 1, "no._explored_programs": 962, "best_cost_per_iteration": [[0, 4], [0, 2], [1, 1], [3, 0]], "no._iterations": 4, "execution_time": 0.026549704999999993, "best_program": "Program([[MoveUp], [Drop, MoveLeft], [MoveDown]])", "test_cost": 0, "test_correct": 1, "train_cost": 0, "train_correct": 1, "test_total": 1, "prune_count": 665}, {"complexity": 2, "task": 6, "trial": 1, "no._explored_programs": 763, "best_cost_per_iteration": [[0, 5], [0, 3], [1, 1], [2, 0]], "no._iterations": 3, "execution_time": 0.020207197999999996, "best_program": "Program([[MoveRight], [Grab, MoveLeft], [Drop, MoveRight]])", "test_cost": 0, "test_correct": 1, "train_cost": 0, "train_correct": 1, "test_total": 1, "prune_count": 480}, {"complexity": 2, "task": 7, "trial": 1, "no._explored_programs": 763, "best_cost_per_iteration": [[0, 5], [0, 3], [1, 1], [2, 0]], "no._iterations": 3, "execution_time": 0.019861885999999995, "best_program": "Program([[MoveRight], [Grab, MoveLeft], [Drop, MoveRight]])", "test_cost": 0, "test_correct": 1, "train_cost": 0, "train_correct": 1, "test_total": 1, "prune_count": 480}, {"complexity": 2, "task": 8, "trial": 1, "no._explored_programs": 493, "best_cost_per_iteration": [[0, 4], [0, 3], [0, 1], [1, 0]], "no._iterations": 2, "execution_time": 0.014153680000000002, "best_program": "Program([[MoveRight, MoveDown], [Drop, MoveUp]])", "test_cost": 0, "test_correct": 1, "train_cost": 0, "train_correct": 1, "test_total": 1, "prune_count": 366}, {"complexity": 2, "task": 9, "trial": 1, "no._explored_programs": 574, "best_cost_per_iteration": [[0, 3], [0, 1], [1, 0]], "no._iterations": 2, "execution_time": 0.01500817900000001, "best_program": "Program([[MoveRight], [Drop, MoveDown]])", "test_cost": 0, "test_correct": 1, "train_cost": 0, "train_correct": 1, "test_total": 1, "prune_count": 285}, {"complexity": 4, "task": 0, "trial": 1, "no._explored_programs": 1988, "best_cost_per_iteration": [[0, 12], [0, 11], [0, 10], [2, 8], [3, 7], [5, 6], [5, 4], [6, 3], [7, 2], [9, 1], [11, 0]], "no._iterations": 12, "execution_time": 0.089063747, "best_program": "Program([[MoveLeft, MoveDown], [MoveDown], [Grab, MoveUp], [MoveUp, MoveRight], [Drop, MoveLeft], [MoveLeft, MoveDown], [MoveDown]])", "test_cost": 0, "test_correct": 1, "train_cost": 0, "train_correct": 1, "test_total": 1, "prune_count": 2711}, {"complexity": 4, "task": 1, "trial": 1, "no._explored_programs": 944, "best_cost_per_iteration": [[0, 9], [0, 8], [0, 7], [0, 5], [1, 4], [1, 2], [2, 1], [3, 0]], "no._iterations": 4, "execution_time": 0.031254271, "best_program": "Program([LoopWhileThen(NotAtLeft [MoveLeft], [Grab]), [MoveDown, MoveDown], [Drop, MoveRight], [MoveRight]])", "test_cost": 0, "test_correct": 1, "train_cost": 0, "train_correct": 1, "test_total": 1, "prune_count": 683}, {"complexity": 4, "task": 2, "trial": 1, "no._explored_programs": 1134, "best_cost_per_iteration": [[0, 6], [0, 5], [1, 3], [2, 2], [3, 1], [3, 0]], "no._iterations": 4, "execution_time": 0.03617935700000001, "best_program": "Program([[Grab, MoveUp], [MoveUp], [Drop, MoveRight], [MoveDown, MoveDown]])", "test_cost": 0, "test_correct": 1, "train_cost": 0, "train_correct": 1, "test_total": 1, "prune_count": 493}, {"complexity": 4, "task": 3, "trial": 1, "no._explored_programs": 945, "best_cost_per_iteration": [[0, 5], [0, 3], [1, 1], [2, 0]], "no._iterations": 3, "execution_time": 0.026410456, "best_program": "Program([[MoveUp], [Grab, MoveUp], [Drop, MoveRight]])", "test_cost": 0, "test_correct": 1, "train_cost": 0, "train_correct": 1, "test_total": 1, "prune_count": 298}, {"complexity": 4, "task": 4, "trial": 1, "no._explored_programs": 1934, "best_cost_per_iteration": [[0, 10], [0, 9], [0, 7], [1, 6], [2, 4], [3, 3], [4, 2], [4, 1], [9, 0]], "no._iterations": 10, "execution_time": 0.08173834, "best_program": "Program([[MoveRight, MoveDown], [Grab, MoveRight], [MoveDown], [Drop, MoveUp], [MoveLeft, MoveLeft], [MoveLeft]])", "test_cost": 0, "test_correct": 1, "train_cost": 0, "train_correct": 1, "test_total": 1, "prune_count": 1997}, {"complexity": 4, "task": 5, "trial": 1, "no._explored_programs": 385, "best_cost_per_iteration": [[0, 2], [0, 1], [0, 0]], "no._iterations": 1, "execution_time": 0.009251619000000003, "best_program": "Program([[MoveLeft, MoveLeft]])", "test_cost": 0, "test_correct": 1, "train_cost": 0, "train_correct": 1, "test_total": 1, "prune_count": 90}, {"complexity": 4, "task": 6, "trial": 1, "no._explored_programs": 665, "best_cost_per_iteration": [[0, 3], [0, 2], [0, 1], [1, 0]], "no._iterations": 2, "execution_time": 0.017127067999999995, "best_program": "Program([[MoveUp, MoveUp], [MoveUp]])", "test_cost": 0, "test_correct": 1, "train_cost": 0, "train_correct": 1, "test_total": 1, "prune_count": 194}, {"complexity": 4, "task": 7, "trial": 1, "no._explored_programs": 2882, "best_cost_per_iteration": [[0, 15], [0, 14], [0, 13], [1, 12], [3, 10], [4, 9], [5, 8], [5, 7], [12, 6]], "no._iterations": 13, "execution_time": 0.11056145199999999, "best_program": "Program([[MoveUp, MoveLeft], [MoveLeft, MoveLeft], [Grab, MoveUp], LoopWhileThen(NotAtRight [MoveRight], [Drop])])", "test_cost": 6, "test_correct": 0, "train_cost": 6, "train_correct": 0, "test_total": 1, "prune_count": 2201}, {"complexity": 4, "task": 8, "trial": 1, "no._explored_programs": 493, "best_cost_per_iteration": [[0, 5], [0, 4], [0, 3], [0, 1], [1, 0]], "no._iterations": 2, "execution_time": 0.01629455299999999, "best_program": "Program([LoopWhileThen(NotAtRight [MoveRight], [MoveDown]), [Drop, MoveDown]])", "test_cost": 0, "test_correct": 1, "train_cost": 0, "train_correct": 1, "test_total": 1, "prune_count": 366}, {"complexity": 4, "task": 9, "trial": 1, "no._explored_programs": 854, "best_cost_per_iteration": [[0, 4], [0, 3], [0, 2], [2, 1], [2, 0]], "no._iterations": 3, "execution_time": 0.020267778000000014, "best_program": "Program([[MoveUp, MoveUp], [MoveRight, MoveRight]])", "test_cost": 0, "test_correct": 1, "train_cost": 0, "train_correct": 1, "test_total": 1, "prune_count": 389}, {"complexity": 6, "task": 0, "trial": 1, "no._explored_programs": 1242, "best_cost_per_iteration": [[0, 11], [0, 9], [1, 8], [2, 7], [2, 6], [2, 3], [3, 2], [4, 1], [4, 0]], "no._iterations": 5, "execution_time": 0.044110844999999996, "best_program": "Program([[MoveUp], [Grab, MoveRight], LoopWhileThen(NotAtRight [MoveRight], [MoveDown]), [Drop, MoveUp], [MoveUp, MoveUp]])", "test_cost": 0, "test_correct": 1, "train_cost": 0, "train_correct": 1, "test_total": 1, "prune_count": 769}, {"complexity": 6, "task": 1, "trial": 1, "no._explored_programs": 1448, "best_cost_per_iteration": [[0, 10], [0, 8], [1, 7], [3, 6], [3, 4], [4, 3], [5, 2], [5, 1], [6, 0]], "no._iterations": 7, "execution_time": 0.059149356, "best_program": "Program([[MoveDown], [Grab, MoveUp], [MoveUp, MoveLeft], [Drop, MoveRight], [MoveRight, MoveDown], [MoveDown]])", "test_cost": 0, "test_correct": 1, "train_cost": 0, "train_correct": 1, "test_total": 1, "prune_count": 1331}, {"complexity": 6, "task": 2, "trial": 1, "no._explored_programs": 2332, "best_cost_per_iteration": [[0, 13], [0, 12], [0, 11], [1, 10], [1, 8], [2, 7], [3, 6], [3, 5], [3, 4]], "no._iterations": 11, "execution_time": 0.108076391, "best_program": "Program([[MoveRight, MoveRight], [MoveDown, MoveDown], [Grab, MoveLeft], [MoveLeft]])", "test_cost": 6, "test_correct": 0, "train_cost": 6, "train_correct": 0, "test_total": 1, "prune_count": 1983}, {"complexity": 6, "task": 3, "trial": 1, "no._explored_programs": 1989, "best_cost_per_iteration": [[0, 22], [0, 21], [0, 20], [0, 19], [0, 17], [1, 16], [1, 15], [1, 13], [2, 12], [2, 11], [3, 10], [3, 9], [3, 8], [5, 7], [6, 5], [7, 4], [8, 3]], "no._iterations": 10, "execution_time": 0.10829960900000002, "best_program": "Program([LoopWhileThen(NotAtTop [MoveUp], [MoveLeft]), LoopWhileThen(NotAtLeft [MoveLeft], [Grab]), [MoveRight, MoveRight], [MoveRight, MoveDown], [MoveDown, MoveDown], [MoveDown], [Drop, MoveRight], [MoveRight]])", "test_cost": 3, "test_correct": 0, "train_cost": 3, "train_correct": 0, "test_total": 1, "prune_count": 1942}, {"complexity": 6, "task": 4, "trial": 1, "no._explored_programs": 871, "best_cost_per_iteration": [[0, 10], [0, 9], [0, 8], [0, 5], [1, 4], [2, 3], [2, 1], [3, 0]], "no._iterations": 4, "execution_time": 0.033381564, "best_program": "Program([LoopWhileThen(NotAtTop [MoveUp], [MoveLeft]), [Grab, MoveRight], [MoveDown, MoveDown], [Drop, MoveLeft]])", "test_cost": 0, "test_correct": 1, "train_cost": 0, "train_correct": 1, "test_total": 1, "prune_count": 756}, {"complexity": 6, "task": 5, "trial": 1, "no._explored_programs": 601, "best_cost_per_iteration": [[0, 8], [0, 7], [0, 6], [0, 4], [1, 3], [1, 2], [2, 1], [2, 0]], "no._iterations": 3, "execution_time": 0.020255632999999995, "best_program": "Program([LoopWhileThen(NotAtRight [MoveRight], [MoveDown]), [MoveDown, MoveDown], [MoveDown, MoveDown]])", "test_cost": 0, "test_correct": 1, "train_cost": 0, "train_correct": 1, "test_total": 1, "prune_count": 642}, {"complexity": 6, "task": 6, "trial": 1, "no._explored_programs": 1006, "best_cost_per_iteration": [[0, 9], [0, 8], [0, 7], [1, 5], [2, 4], [3, 2], [4, 1], [5, 0]], "no._iterations": 6, "execution_time": 0.041960208, "best_program": "Program([[MoveRight, MoveDown], [MoveDown], [Grab, MoveDown], [MoveDown], [Drop, MoveLeft], [MoveLeft]])", "test_cost": 0, "test_correct": 1, "train_cost": 0, "train_correct": 1, "test_total": 1, "prune_count": 1389}, {"complexity": 6, "task": 7, "trial": 1, "no._explored_programs": 2423, "best_cost_per_iteration": [[0, 17], [0, 16], [0, 15], [0, 12], [1, 11], [1, 9], [2, 8], [3, 7], [3, 6]], "no._iterations": 11, "execution_time": 0.109780715, "best_program": "Program([LoopWhileThen(NotAtLeft [MoveLeft], [MoveDown]), [MoveDown, MoveDown], [Grab, MoveUp]])", "test_cost": 8, "test_correct": 0, "train_cost": 8, "train_correct": 0, "test_total": 1, "prune_count": 1892}, {"complexity": 6, "task": 8, "trial": 1, "no._explored_programs": 1934, "best_cost_per_iteration": [[0, 9], [0, 8], [0, 6], [1, 4], [2, 3], [3, 2], [3, 1], [9, 0]], "no._iterations": 10, "execution_time": 0.08176115699999999, "best_program": "Program([[MoveLeft, MoveDown], [Grab, MoveDown], [Drop, MoveUp], [MoveRight, MoveRight], [MoveRight]])", "test_cost": 0, "test_correct": 1, "train_cost": 0, "train_correct": 1, "test_total": 1, "prune_count": 1997}, {"complexity": 6, "task": 9, "trial": 1, "no._explored_programs": 1168, "best_cost_per_iteration": [[0, 8], [0, 6], [1, 5], [3, 4], [3, 2], [4, 1], [5, 0]], "no._iterations": 6, "execution_time": 0.043933866, "best_program": "Program([[MoveRight], [Grab, MoveLeft], [MoveLeft, MoveDown], [Drop, MoveLeft], [MoveLeft]])", "test_cost": 0, "test_correct": 1, "train_cost": 0, "train_correct": 1, "test_total": 1, "prune_count": 1227}, {"complexity": 8, "task": 0, "trial": 1, "no._explored_programs": 2413, "best_cost_per_iteration": [[0, 18], [0, 17], [0, 15], [1, 14], [2, 13], [2, 12], [2, 11], [4, 10]], "no._iterations": 11, "execution_time": 0.10741117299999998, "best_program": "Program([[MoveUp, MoveRight], [Grab, MoveRight], [MoveRight, MoveRight], [MoveRight, MoveRight], [MoveDown]])", "test_cost": 11, "test_correct": 0, "train_cost": 11, "train_correct": 0, "test_total": 1, "prune_count": 1902}, {"complexity": 8, "task": 1, "trial": 1, "no._explored_programs": 2088, "best_cost_per_iteration": [[0, 17], [0, 16], [0, 15], [0, 14], [2, 13], [2, 11], [3, 10], [3, 9], [4, 8], [4, 7], [5, 5], [6, 4], [7, 3], [9, 2]], "no._iterations": 10, "execution_time": 0.10271604000000001, "best_program": "Program([[MoveUp, MoveLeft], LoopWhileThen(NotAtLeft [MoveLeft], [Grab]), [MoveRight, MoveRight], [MoveRight, MoveRight], [MoveDown], [Drop, MoveUp], [MoveLeft, MoveLeft]])", "test_cost": 2, "test_correct": 0, "train_cost": 2, "train_correct": 0, "test_total": 1, "prune_count": 1843}, {"complexity": 8, "task": 2, "trial": 1, "no._explored_programs": 1664, "best_cost_per_iteration": [[0, 22], [0, 21], [0, 20], [0, 15], [1, 13], [2, 12], [4, 11], [4, 10], [4, 7], [5, 5], [6, 4], [7, 3], [7, 2], [8, 1], [8, 0]], "no._iterations": 9, "execution_time": 0.08524707900000002, "best_program": "Program([LoopWhileThen(NotAtRight [MoveRight], [MoveDown]), [MoveDown], [Grab, MoveUp], LoopWhileThen(NotAtTop [MoveUp], [MoveLeft]), [MoveDown], [Drop, MoveRight], [MoveDown, MoveDown], [MoveDown, MoveDown]])", "test_cost": 0, "test_correct": 1, "train_cost": 0, "train_correct": 1, "test_total": 1, "prune_count": 1883}, {"complexity": 8, "task": 3, "trial": 1, "no._explored_programs": 2468, "best_cost_per_iteration": [[0, 29], [0, 28], [0, 27], [2, 26], [2, 25], [4, 23], [5, 22], [6, 21], [6, 20], [6, 19]], "no._iterations": 12, "execution_time": 0.10049680400000001, "best_program": "Program([[MoveUp, MoveUp], [MoveUp, MoveUp], [MoveRight], [Grab, MoveDown], [MoveDown]])", "test_cost": 21, "test_correct": 0, "train_cost": 21, "train_correct": 0, "test_total": 1, "prune_count": 2231}, {"complexity": 8, "task": 4, "trial": 1, "no._explored_programs": 2754, "best_cost_per_iteration": [[0, 13], [0, 12], [0, 11], [2, 10], [4, 9], [6, 8], [8, 6], [9, 4], [10, 3], [11, 2], [11, 1], [12, 0]], "no._iterations": 13, "execution_time": 0.101681887, "best_program": "Program([[MoveUp, MoveUp], [MoveUp, MoveUp], [MoveRight, MoveRight], [Grab, MoveDown], [Drop, MoveLeft], [MoveLeft, MoveLeft], [MoveLeft]])", "test_cost": 0, "test_correct": 1, "train_cost": 0, "train_correct": 1, "test_total": 1, "prune_count": 2329}, {"complexity": 8, "task": 5, "trial": 1, "no._explored_programs": 1908, "best_cost_per_iteration": [[0, 29], [0, 28], [0, 27], [0, 22], [1, 21], [1, 20], [2, 18], [3, 17], [4, 16], [4, 15], [4, 14], [4, 13], [9, 12]], "no._iterations": 10, "execution_time": 0.10329556100000001, "best_program": "Program([LoopWhileThen(NotAtLeft [MoveLeft], [MoveDown]), [MoveDown, MoveDown], [MoveDown], [Grab, MoveRight], [MoveRight, MoveRight], [MoveRight, MoveRight], [MoveRight]])", "test_cost": 12, "test_correct": 0, "train_cost": 12, "train_correct": 0, "test_total": 1, "prune_count": 2023}, {"complexity": 8, "task": 6, "trial": 1, "no._explored_programs": 2960, "best_cost_per_iteration": [[0, 20], [0, 19], [0, 18], [1, 17], [1, 16], [2, 15], [8, 14], [9, 13]], "no._iterations": 15, "execution_time": 0.10576572699999999, "best_program": "Program([[MoveUp, MoveUp], [MoveRight, MoveRight], [MoveRight, MoveRight], [MoveDown]])", "test_cost": 15, "test_correct": 0, "train_cost": 15, "train_correct": 0, "test_total": 1, "prune_count": 2891}, {"complexity": 8, "task": 7, "trial": 1, "no._explored_programs": 1989, "best_cost_per_iteration": [[0, 24], [0, 23], [0, 22], [0, 17], [1, 16], [1, 14], [2, 13], [3, 12], [3, 11]], "no._iterations": 10, "execution_time": 0.10151791, "best_program": "Program([LoopWhileThen(NotAtLeft [MoveLeft], [MoveDown]), [MoveDown, MoveDown], [Grab, MoveRight], [MoveRight, MoveRight], [MoveDown]])", "test_cost": 12, "test_correct": 0, "train_cost": 12, "train_correct": 0, "test_total": 1, "prune_count": 1942}, {"complexity": 8, "task": 8, "trial": 1, "no._explored_programs": 1718, "best_cost_per_iteration": [[0, 10], [0, 9], [0, 8], [2, 6], [3, 5], [4, 4], [4, 2], [5, 1], [7, 0]], "no._iterations": 8, "execution_time": 0.06574961100000001, "best_program": "Program([[MoveUp, MoveUp], [MoveRight], [Grab, MoveLeft], [MoveLeft, MoveLeft], [Drop, MoveLeft], [MoveDown]])", "test_cost": 0, "test_correct": 1, "train_cost": 0, "train_correct": 1, "test_total": 1, "prune_count": 1445}, {"complexity": 8, "task": 9, "trial": 1, "no._explored_programs": 898, "best_cost_per_iteration": [[0, 10], [0, 9], [0, 8], [1, 7], [1, 6], [2, 5], [2, 3], [3, 2], [4, 0]], "no._iterations": 5, "execution_time": 0.03445770399999999, "best_program": "Program([[MoveDown, MoveDown], [MoveDown, MoveDown], [MoveDown, MoveDown], [Grab, MoveRight], [MoveDown]])", "test_cost": 0, "test_correct": 1, "train_cost": 0, "train_correct": 1, "test_total": 1, "prune_count": 1113}, {"complexity": 10, "task": 0, "trial": 1, "no._explored_programs": 2302, "best_cost_per_iteration": [[0, 24], [0, 23], [0, 22], [0, 17], [1, 16], [1, 15], [2, 14]], "no._iterations": 18, "execution_time": 0.10156057499999999, "best_program": "Program([[MoveLeft, MoveLeft], [MoveLeft, MoveDown], [MoveDown, MoveDown]])", "test_cost": 18, "test_correct": 0, "train_cost": 18, "train_correct": 0, "test_total": 1, "prune_count": 4701}, {"complexity": 10, "task": 1, "trial": 1, "no._explored_programs": 601, "best_cost_per_iteration": [[0, 13], [0, 12], [0, 11], [0, 3], [1, 2], [1, 1], [2, 0]], "no._iterations": 3, "execution_time": 0.020492365, "best_program": "Program([LoopWhileThen(NotAtLeft [MoveLeft], [MoveDown]), [MoveDown, MoveDown], [MoveDown]])", "test_cost": 0, "test_correct": 1, "train_cost": 0, "train_correct": 1, "test_total": 1, "prune_count": 642}, {"complexity": 10, "task": 2, "trial": 1, "no._explored_programs": 2205, "best_cost_per_iteration": [[0, 18], [0, 17], [0, 16], [1, 15], [1, 13], [2, 12], [3, 11], [6, 10], [8, 9], [11, 7]], "no._iterations": 12, "execution_time": 0.111722731, "best_program": "Program([[MoveRight, MoveRight], [MoveRight, MoveRight], [Grab, MoveLeft], [MoveLeft, MoveLeft], [MoveDown, MoveDown]])", "test_cost": 7, "test_correct": 0, "train_cost": 7, "train_correct": 0, "test_total": 1, "prune_count": 2494}, {"complexity": 10, "task": 3, "trial": 1, "no._explored_programs": 1936, "best_cost_per_iteration": [[0, 20], [0, 19], [0, 18], [0, 12], [1, 11], [1, 10], [2, 9], [2, 7], [3, 6], [5, 5], [5, 4], [5, 1]], "no._iterations": 10, "execution_time": 0.104650183, "best_program": "Program([LoopWhileThen(NotAtBottom [MoveDown], [Grab]), [MoveUp, MoveUp], [MoveUp, MoveUp], [Drop, MoveLeft], [MoveLeft, MoveDown]])", "test_cost": 4, "test_correct": 0, "train_cost": 4, "train_correct": 0, "test_total": 1, "prune_count": 1995}, {"complexity": 10, "task": 4, "trial": 1, "no._explored_programs": 2008, "best_cost_per_iteration": [[0, 24], [0, 23], [0, 22], [0, 20], [1, 19], [2, 18], [2, 17], [2, 15], [5, 14], [5, 13]], "no._iterations": 11, "execution_time": 0.109903081, "best_program": "Program([LoopWhileThen(NotAtTop [MoveUp], [MoveRight]), [Grab, MoveDown], [MoveDown, MoveDown], [MoveDown, MoveDown], [MoveDown, MoveDown], [MoveDown]])", "test_cost": 14, "test_correct": 0, "train_cost": 14, "train_correct": 0, "test_total": 1, "prune_count": 2307}, {"complexity": 10, "task": 5, "trial": 1, "no._explored_programs": 2386, "best_cost_per_iteration": [[0, 14], [0, 13], [0, 12], [1, 11], [1, 10], [2, 8], [3, 6], [4, 5], [5, 4], [5, 3], [6, 2], [6, 1]], "no._iterations": 11, "execution_time": 0.11189565300000001, "best_program": "Program([[MoveUp, MoveUp], [MoveUp, MoveUp], [MoveUp], [Grab, MoveDown], [Drop, MoveLeft], [MoveLeft, MoveLeft], [MoveLeft, MoveLeft], [MoveLeft]])", "test_cost": 2, "test_correct": 0, "train_cost": 2, "train_correct": 0, "test_total": 1, "prune_count": 1929}, {"complexity": 10, "task": 6, "trial": 1, "no._explored_programs": 1620, "best_cost_per_iteration": [[0, 8], [0, 6], [1, 5], [3, 4], [3, 2], [4, 1], [6, 0]], "no._iterations": 7, "execution_time": 0.06362784599999999, "best_program": "Program([[MoveDown], [Grab, MoveUp], [MoveUp, MoveLeft], [Drop, MoveUp], [MoveRight]])", "test_cost": 0, "test_correct": 1, "train_cost": 0, "train_correct": 1, "test_total": 1, "prune_count": 1159}, {"complexity": 10, "task": 7, "trial": 1, "no._explored_programs": 1897, "best_cost_per_iteration": [[0, 18], [0, 17], [0, 16], [1, 15], [1, 13], [2, 12], [3, 11], [3, 9], [4, 8], [5, 7], [5, 6], [6, 5], [6, 4]], "no._iterations": 12, "execution_time": 0.105755493, "best_program": "Program([[MoveRight, MoveRight], [MoveRight, MoveRight], [Grab, MoveLeft], [MoveLeft, MoveLeft], [Drop, MoveDown], [MoveDown]])", "test_cost": 7, "test_correct": 0, "train_cost": 7, "train_correct": 0, "test_total": 1, "prune_count": 2802}, {"complexity": 10, "task": 8, "trial": 1, "no._explored_programs": 2221, "best_cost_per_iteration": [[0, 22], [0, 21], [0, 20], [0, 14], [13, 12], [14, 11]], "no._iterations": 15, "execution_time": 0.10194075800000002, "best_program": "Program([[MoveLeft, MoveLeft], [MoveLeft, MoveLeft], [MoveLeft, MoveLeft], [MoveLeft, MoveLeft], [MoveDown], [Grab, MoveRight]])", "test_cost": 11, "test_correct": 0, "train_cost": 11, "train_correct": 0, "test_total": 1, "prune_count": 3630}, {"complexity": 10, "task": 9, "trial": 1, "no._explored_programs": 2024, "best_cost_per_iteration": [[0, 33], [0, 32], [0, 31], [0, 25], [1, 24], [1, 23], [1, 22], [4, 21], [5, 19], [6, 18], [7, 17], [7, 16], [7, 11]], "no._iterations": 11, "execution_time": 0.103553274, "best_program": "Program([LoopWhileThen(NotAtTop [MoveUp], [MoveRight]), [MoveRight, MoveRight], [MoveRight, MoveRight], [MoveDown], [Grab, MoveDown], LoopWhileThen(NotAtBottom [MoveDown], [Drop]), [MoveLeft]])", "test_cost": 13, "test_correct": 0, "train_cost": 13, "train_correct": 0, "test_total": 1, "prune_count": 2291}]]