[[{"complexity": 1, "task": 0, "trial": 1, "no._explored_programs": 1, "best_cost_per_iteration": [[0, 1]], "no._iterations": 13, "execution_time": 0.10127916699999999, "best_program": "Program([[MoveRight, Draw]])", "test_cost": 1, "test_correct": 0, "train_cost": 1, "train_correct": 0, "test_total": 1, "prune_count": 54}, {"complexity": 1, "task": 1, "trial": 1, "no._explored_programs": 1, "best_cost_per_iteration": [[0, 1]], "no._iterations": 13, "execution_time": 0.101185723, "best_program": "Program([[MoveRight, Draw]])", "test_cost": 1, "test_correct": 0, "train_cost": 1, "train_correct": 0, "test_total": 1, "prune_count": 54}, {"complexity": 1, "task": 2, "trial": 1, "no._explored_programs": 1, "best_cost_per_iteration": [[0, 1]], "no._iterations": 13, "execution_time": 0.101188665, "best_program": "Program([[MoveRight, Draw]])", "test_cost": 1, "test_correct": 0, "train_cost": 1, "train_correct": 0, "test_total": 1, "prune_count": 54}, {"complexity": 1, "task": 3, "trial": 1, "no._explored_programs": 1, "best_cost_per_iteration": [[0, 1]], "no._iterations": 13, "execution_time": 0.102777849, "best_program": "Program([[MoveRight, Draw]])", "test_cost": 1, "test_correct": 0, "train_cost": 1, "train_correct": 0, "test_total": 1, "prune_count": 54}, {"complexity": 1, "task": 4, "trial": 1, "no._explored_programs": 1, "best_cost_per_iteration": [[0, 1]], "no._iterations": 13, "execution_time": 0.102035977, "best_program": "Program([[MoveRight, Draw]])", "test_cost": 1, "test_correct": 0, "train_cost": 1, "train_correct": 0, "test_total": 1, "prune_count": 54}, {"complexity": 1, "task": 5, "trial": 1, "no._explored_programs": 1, "best_cost_per_iteration": [[0, 1]], "no._iterations": 13, "execution_time": 0.10152670700000001, "best_program": "Program([[MoveRight, Draw]])", "test_cost": 1, "test_correct": 0, "train_cost": 1, "train_correct": 0, "test_total": 1, "prune_count": 54}, {"complexity": 1, "task": 6, "trial": 1, "no._explored_programs": 1, "best_cost_per_iteration": [[0, 1]], "no._iterations": 13, "execution_time": 0.10126809199999999, "best_program": "Program([[MoveRight, Draw]])", "test_cost": 1, "test_correct": 0, "train_cost": 1, "train_correct": 0, "test_total": 1, "prune_count": 54}, {"complexity": 1, "task": 7, "trial": 1, "no._explored_programs": 1, "best_cost_per_iteration": [[0, 1]], "no._iterations": 13, "execution_time": 0.10067664200000001, "best_program": "Program([[MoveRight, Draw]])", "test_cost": 1, "test_correct": 0, "train_cost": 1, "train_correct": 0, "test_total": 1, "prune_count": 54}, {"complexity": 1, "task": 8, "trial": 1, "no._explored_programs": 1, "best_cost_per_iteration": [[0, 1]], "no._iterations": 13, "execution_time": 0.101950511, "best_program": "Program([[MoveRight, Draw]])", "test_cost": 1, "test_correct": 0, "train_cost": 1, "train_correct": 0, "test_total": 1, "prune_count": 54}, {"complexity": 1, "task": 9, "trial": 1, "no._explored_programs": 1, "best_cost_per_iteration": [[0, 1]], "no._iterations": 13, "execution_time": 0.10140582599999999, "best_program": "Program([[MoveRight, Draw]])", "test_cost": 1, "test_correct": 0, "train_cost": 1, "train_correct": 0, "test_total": 1, "prune_count": 54}, {"complexity": 2, "task": 0, "trial": 1, "no._explored_programs": 1, "best_cost_per_iteration": [[0, 1]], "no._iterations": 8, "execution_time": 0.11674303600000002, "best_program": "Program([[MoveDown, Draw]])", "test_cost": 1, "test_correct": 0, "train_cost": 1, "train_correct": 0, "test_total": 1, "prune_count": 54}, {"complexity": 2, "task": 1, "trial": 1, "no._explored_programs": 1, "best_cost_per_iteration": [[0, 1]], "no._iterations": 9, "execution_time": 0.111532737, "best_program": "Program([LoopWhileThen(NotAtBottom [MoveDown], [Draw])])", "test_cost": 1, "test_correct": 0, "train_cost": 1, "train_correct": 0, "test_total": 1, "prune_count": 54}, {"complexity": 2, "task": 2, "trial": 1, "no._explored_programs": 1, "best_cost_per_iteration": [[0, 1]], "no._iterations": 9, "execution_time": 0.111530685, "best_program": "Program([LoopWhileThen(NotAtBottom [MoveDown], [Draw])])", "test_cost": 1, "test_correct": 0, "train_cost": 1, "train_correct": 0, "test_total": 1, "prune_count": 54}, {"complexity": 2, "task": 3, "trial": 1, "no._explored_programs": 1, "best_cost_per_iteration": [[0, 1]], "no._iterations": 9, "execution_time": 0.111785286, "best_program": "Program([LoopWhileThen(NotAtBottom [MoveDown], [Draw])])", "test_cost": 1, "test_correct": 0, "train_cost": 1, "train_correct": 0, "test_total": 1, "prune_count": 54}, {"complexity": 2, "task": 4, "trial": 1, "no._explored_programs": 1, "best_cost_per_iteration": [[0, 1]], "no._iterations": 9, "execution_time": 0.11113020800000001, "best_program": "Program([LoopWhileThen(NotAtBottom [MoveDown], [Draw])])", "test_cost": 1, "test_correct": 0, "train_cost": 1, "train_correct": 0, "test_total": 1, "prune_count": 54}, {"complexity": 2, "task": 5, "trial": 1, "no._explored_programs": 1, "best_cost_per_iteration": [[0, 1]], "no._iterations": 9, "execution_time": 0.111786949, "best_program": "Program([LoopWhileThen(NotAtBottom [MoveDown], [Draw])])", "test_cost": 1, "test_correct": 0, "train_cost": 1, "train_correct": 0, "test_total": 1, "prune_count": 54}, {"complexity": 2, "task": 6, "trial": 1, "no._explored_programs": 1, "best_cost_per_iteration": [[0, 1]], "no._iterations": 9, "execution_time": 0.11066543000000001, "best_program": "Program([LoopWhileThen(NotAtBottom [MoveDown], [Draw])])", "test_cost": 1, "test_correct": 0, "train_cost": 1, "train_correct": 0, "test_total": 1, "prune_count": 54}, {"complexity": 2, "task": 7, "trial": 1, "no._explored_programs": 1, "best_cost_per_iteration": [[0, 1]], "no._iterations": 9, "execution_time": 0.11117979299999997, "best_program": "Program([LoopWhileThen(NotAtBottom [MoveDown], [Draw])])", "test_cost": 1, "test_correct": 0, "train_cost": 1, "train_correct": 0, "test_total": 1, "prune_count": 54}, {"complexity": 2, "task": 8, "trial": 1, "no._explored_programs": 1, "best_cost_per_iteration": [[0, 1]], "no._iterations": 9, "execution_time": 0.11175601399999999, "best_program": "Program([LoopWhileThen(NotAtBottom [MoveDown], [Draw])])", "test_cost": 1, "test_correct": 0, "train_cost": 1, "train_correct": 0, "test_total": 1, "prune_count": 54}, {"complexity": 2, "task": 9, "trial": 1, "no._explored_programs": 1, "best_cost_per_iteration": [[0, 1]], "no._iterations": 9, "execution_time": 0.111575802, "best_program": "Program([LoopWhileThen(NotAtBottom [MoveDown], [Draw])])", "test_cost": 1, "test_correct": 0, "train_cost": 1, "train_correct": 0, "test_total": 1, "prune_count": 54}, {"complexity": 3, "task": 0, "trial": 1, "no._explored_programs": 1, "best_cost_per_iteration": [[0, 1]], "no._iterations": 7, "execution_time": 0.118038755, "best_program": "Program([[MoveRight, MoveRight]])", "test_cost": 1, "test_correct": 0, "train_cost": 1, "train_correct": 0, "test_total": 1, "prune_count": 54}, {"complexity": 3, "task": 1, "trial": 1, "no._explored_programs": 1, "best_cost_per_iteration": [[0, 1]], "no._iterations": 6, "execution_time": 0.101775816, "best_program": "Program([[Draw, MoveRight]])", "test_cost": 1, "test_correct": 0, "train_cost": 1, "train_correct": 0, "test_total": 1, "prune_count": 54}, {"complexity": 3, "task": 2, "trial": 1, "no._explored_programs": 1, "best_cost_per_iteration": [[0, 1]], "no._iterations": 6, "execution_time": 0.101182643, "best_program": "Program([[Draw, MoveRight]])", "test_cost": 1, "test_correct": 0, "train_cost": 1, "train_correct": 0, "test_total": 1, "prune_count": 54}, {"complexity": 3, "task": 3, "trial": 1, "no._explored_programs": 1, "best_cost_per_iteration": [[0, 1]], "no._iterations": 6, "execution_time": 0.10121440699999999, "best_program": "Program([[Draw, MoveRight]])", "test_cost": 1, "test_correct": 0, "train_cost": 1, "train_correct": 0, "test_total": 1, "prune_count": 54}, {"complexity": 3, "task": 4, "trial": 1, "no._explored_programs": 1, "best_cost_per_iteration": [[0, 1]], "no._iterations": 6, "execution_time": 0.10124939, "best_program": "Program([[Draw, MoveRight]])", "test_cost": 1, "test_correct": 0, "train_cost": 1, "train_correct": 0, "test_total": 1, "prune_count": 54}, {"complexity": 3, "task": 5, "trial": 1, "no._explored_programs": 1, "best_cost_per_iteration": [[0, 1]], "no._iterations": 6, "execution_time": 0.100141361, "best_program": "Program([[Draw, MoveRight]])", "test_cost": 1, "test_correct": 0, "train_cost": 1, "train_correct": 0, "test_total": 1, "prune_count": 54}, {"complexity": 3, "task": 6, "trial": 1, "no._explored_programs": 1, "best_cost_per_iteration": [[0, 1]], "no._iterations": 6, "execution_time": 0.10135044800000001, "best_program": "Program([[Draw, MoveRight]])", "test_cost": 1, "test_correct": 0, "train_cost": 1, "train_correct": 0, "test_total": 1, "prune_count": 54}, {"complexity": 3, "task": 7, "trial": 1, "no._explored_programs": 1, "best_cost_per_iteration": [[0, 1]], "no._iterations": 6, "execution_time": 0.101530952, "best_program": "Program([[Draw, MoveRight]])", "test_cost": 1, "test_correct": 0, "train_cost": 1, "train_correct": 0, "test_total": 1, "prune_count": 54}, {"complexity": 3, "task": 8, "trial": 1, "no._explored_programs": 1, "best_cost_per_iteration": [[0, 1]], "no._iterations": 6, "execution_time": 0.101163779, "best_program": "Program([[Draw, MoveRight]])", "test_cost": 1, "test_correct": 0, "train_cost": 1, "train_correct": 0, "test_total": 1, "prune_count": 54}, {"complexity": 3, "task": 9, "trial": 1, "no._explored_programs": 1, "best_cost_per_iteration": [[0, 1]], "no._iterations": 6, "execution_time": 0.101443485, "best_program": "Program([[Draw, MoveRight]])", "test_cost": 1, "test_correct": 0, "train_cost": 1, "train_correct": 0, "test_total": 1, "prune_count": 54}, {"complexity": 4, "task": 0, "trial": 1, "no._explored_programs": 1, "best_cost_per_iteration": [[0, 1]], "no._iterations": 5, "execution_time": 0.105225971, "best_program": "Program([[MoveDown, MoveDown]])", "test_cost": 1, "test_correct": 0, "train_cost": 1, "train_correct": 0, "test_total": 1, "prune_count": 54}, {"complexity": 4, "task": 1, "trial": 1, "no._explored_programs": 1, "best_cost_per_iteration": [[0, 1]], "no._iterations": 5, "execution_time": 0.10437000699999999, "best_program": "Program([[MoveDown, MoveDown]])", "test_cost": 1, "test_correct": 0, "train_cost": 1, "train_correct": 0, "test_total": 1, "prune_count": 54}, {"complexity": 4, "task": 2, "trial": 1, "no._explored_programs": 1, "best_cost_per_iteration": [[0, 1]], "no._iterations": 5, "execution_time": 0.10475610700000001, "best_program": "Program([[MoveDown, MoveDown]])", "test_cost": 1, "test_correct": 0, "train_cost": 1, "train_correct": 0, "test_total": 1, "prune_count": 54}, {"complexity": 4, "task": 3, "trial": 1, "no._explored_programs": 1, "best_cost_per_iteration": [[0, 1]], "no._iterations": 5, "execution_time": 0.104962644, "best_program": "Program([[MoveDown, MoveDown]])", "test_cost": 1, "test_correct": 0, "train_cost": 1, "train_correct": 0, "test_total": 1, "prune_count": 54}, {"complexity": 4, "task": 4, "trial": 1, "no._explored_programs": 1, "best_cost_per_iteration": [[0, 1]], "no._iterations": 5, "execution_time": 0.106464605, "best_program": "Program([[MoveDown, MoveDown]])", "test_cost": 1, "test_correct": 0, "train_cost": 1, "train_correct": 0, "test_total": 1, "prune_count": 54}, {"complexity": 4, "task": 5, "trial": 1, "no._explored_programs": 1, "best_cost_per_iteration": [[0, 1]], "no._iterations": 5, "execution_time": 0.11982808, "best_program": "Program([[MoveDown, MoveDown]])", "test_cost": 1, "test_correct": 0, "train_cost": 1, "train_correct": 0, "test_total": 1, "prune_count": 54}, {"complexity": 4, "task": 6, "trial": 1, "no._explored_programs": 1, "best_cost_per_iteration": [[0, 1]], "no._iterations": 5, "execution_time": 0.107037021, "best_program": "Program([[MoveDown, MoveDown]])", "test_cost": 1, "test_correct": 0, "train_cost": 1, "train_correct": 0, "test_total": 1, "prune_count": 54}, {"complexity": 4, "task": 7, "trial": 1, "no._explored_programs": 1, "best_cost_per_iteration": [[0, 1]], "no._iterations": 5, "execution_time": 0.10679127899999999, "best_program": "Program([[MoveDown, MoveDown]])", "test_cost": 1, "test_correct": 0, "train_cost": 1, "train_correct": 0, "test_total": 1, "prune_count": 54}, {"complexity": 4, "task": 8, "trial": 1, "no._explored_programs": 1, "best_cost_per_iteration": [[0, 1]], "no._iterations": 5, "execution_time": 0.10533682600000001, "best_program": "Program([[MoveDown, MoveDown]])", "test_cost": 1, "test_correct": 0, "train_cost": 1, "train_correct": 0, "test_total": 1, "prune_count": 54}, {"complexity": 4, "task": 9, "trial": 1, "no._explored_programs": 1, "best_cost_per_iteration": [[0, 1]], "no._iterations": 5, "execution_time": 0.107634166, "best_program": "Program([[MoveDown, MoveDown]])", "test_cost": 1, "test_correct": 0, "train_cost": 1, "train_correct": 0, "test_total": 1, "prune_count": 54}, {"complexity": 5, "task": 0, "trial": 1, "no._explored_programs": 1, "best_cost_per_iteration": [[0, 1]], "no._iterations": 5, "execution_time": 0.128319216, "best_program": "Program([[MoveDown, MoveDown]])", "test_cost": 1, "test_correct": 0, "train_cost": 1, "train_correct": 0, "test_total": 1, "prune_count": 54}, {"complexity": 5, "task": 1, "trial": 1, "no._explored_programs": 1, "best_cost_per_iteration": [[0, 1]], "no._iterations": 5, "execution_time": 0.127252288, "best_program": "Program([[MoveDown, MoveDown]])", "test_cost": 1, "test_correct": 0, "train_cost": 1, "train_correct": 0, "test_total": 1, "prune_count": 54}, {"complexity": 5, "task": 2, "trial": 1, "no._explored_programs": 1, "best_cost_per_iteration": [[0, 1]], "no._iterations": 4, "execution_time": 0.101709148, "best_program": "Program([[MoveDown]])", "test_cost": 1, "test_correct": 0, "train_cost": 1, "train_correct": 0, "test_total": 1, "prune_count": 54}, {"complexity": 5, "task": 3, "trial": 1, "no._explored_programs": 1, "best_cost_per_iteration": [[0, 1]], "no._iterations": 4, "execution_time": 0.100262659, "best_program": "Program([[MoveDown]])", "test_cost": 1, "test_correct": 0, "train_cost": 1, "train_correct": 0, "test_total": 1, "prune_count": 54}, {"complexity": 5, "task": 4, "trial": 1, "no._explored_programs": 1, "best_cost_per_iteration": [[0, 1]], "no._iterations": 4, "execution_time": 0.10318973, "best_program": "Program([[MoveDown]])", "test_cost": 1, "test_correct": 0, "train_cost": 1, "train_correct": 0, "test_total": 1, "prune_count": 54}, {"complexity": 5, "task": 5, "trial": 1, "no._explored_programs": 1, "best_cost_per_iteration": [[0, 1]], "no._iterations": 4, "execution_time": 0.10069396500000001, "best_program": "Program([[MoveDown]])", "test_cost": 1, "test_correct": 0, "train_cost": 1, "train_correct": 0, "test_total": 1, "prune_count": 54}, {"complexity": 5, "task": 6, "trial": 1, "no._explored_programs": 1, "best_cost_per_iteration": [[0, 1]], "no._iterations": 5, "execution_time": 0.127767715, "best_program": "Program([[MoveDown, MoveDown]])", "test_cost": 1, "test_correct": 0, "train_cost": 1, "train_correct": 0, "test_total": 1, "prune_count": 54}, {"complexity": 5, "task": 7, "trial": 1, "no._explored_programs": 1, "best_cost_per_iteration": [[0, 1]], "no._iterations": 5, "execution_time": 0.12822706, "best_program": "Program([[MoveDown, MoveDown]])", "test_cost": 1, "test_correct": 0, "train_cost": 1, "train_correct": 0, "test_total": 1, "prune_count": 54}, {"complexity": 5, "task": 8, "trial": 1, "no._explored_programs": 1, "best_cost_per_iteration": [[0, 1]], "no._iterations": 5, "execution_time": 0.12777979, "best_program": "Program([[MoveDown, MoveDown]])", "test_cost": 1, "test_correct": 0, "train_cost": 1, "train_correct": 0, "test_total": 1, "prune_count": 54}, {"complexity": 5, "task": 9, "trial": 1, "no._explored_programs": 1, "best_cost_per_iteration": [[0, 1]], "no._iterations": 5, "execution_time": 0.126715807, "best_program": "Program([[MoveDown, MoveDown]])", "test_cost": 1, "test_correct": 0, "train_cost": 1, "train_correct": 0, "test_total": 1, "prune_count": 54}]]