[[{"complexity": 1, "task": 0, "trial": 1, "no._explored_programs": 1, "best_cost_per_iteration": [[0, 1]], "no._iterations": 13, "execution_time": 0.107120435, "best_program": "Program([[MoveDown, MoveRight]])", "test_cost": 1, "test_correct": 0, "train_cost": 1, "train_correct": 0, "test_total": 1, "prune_count": 36}, {"complexity": 1, "task": 1, "trial": 1, "no._explored_programs": 1, "best_cost_per_iteration": [[0, 1]], "no._iterations": 13, "execution_time": 0.10727853999999999, "best_program": "Program([[MoveDown, MoveRight]])", "test_cost": 1, "test_correct": 0, "train_cost": 1, "train_correct": 0, "test_total": 1, "prune_count": 36}, {"complexity": 1, "task": 2, "trial": 1, "no._explored_programs": 1, "best_cost_per_iteration": [[0, 1]], "no._iterations": 13, "execution_time": 0.107079223, "best_program": "Program([[MoveDown, MoveRight]])", "test_cost": 1, "test_correct": 0, "train_cost": 1, "train_correct": 0, "test_total": 1, "prune_count": 36}, {"complexity": 1, "task": 3, "trial": 1, "no._explored_programs": 1, "best_cost_per_iteration": [[0, 1]], "no._iterations": 13, "execution_time": 0.107325471, "best_program": "Program([[MoveDown, MoveRight]])", "test_cost": 1, "test_correct": 0, "train_cost": 1, "train_correct": 0, "test_total": 1, "prune_count": 36}, {"complexity": 1, "task": 4, "trial": 1, "no._explored_programs": 1, "best_cost_per_iteration": [[0, 1]], "no._iterations": 13, "execution_time": 0.107220182, "best_program": "Program([[MoveDown, MoveRight]])", "test_cost": 1, "test_correct": 0, "train_cost": 1, "train_correct": 0, "test_total": 1, "prune_count": 36}, {"complexity": 1, "task": 5, "trial": 1, "no._explored_programs": 1, "best_cost_per_iteration": [[0, 1]], "no._iterations": 13, "execution_time": 0.107140046, "best_program": "Program([[MoveDown, MoveRight]])", "test_cost": 1, "test_correct": 0, "train_cost": 1, "train_correct": 0, "test_total": 1, "prune_count": 36}, {"complexity": 1, "task": 6, "trial": 1, "no._explored_programs": 1, "best_cost_per_iteration": [[0, 1]], "no._iterations": 13, "execution_time": 0.107871535, "best_program": "Program([[MoveDown, MoveRight]])", "test_cost": 1, "test_correct": 0, "train_cost": 1, "train_correct": 0, "test_total": 1, "prune_count": 36}, {"complexity": 1, "task": 7, "trial": 1, "no._explored_programs": 1, "best_cost_per_iteration": [[0, 1]], "no._iterations": 13, "execution_time": 0.107222521, "best_program": "Program([[MoveDown, MoveRight]])", "test_cost": 1, "test_correct": 0, "train_cost": 1, "train_correct": 0, "test_total": 1, "prune_count": 36}, {"complexity": 1, "task": 8, "trial": 1, "no._explored_programs": 1, "best_cost_per_iteration": [[0, 1]], "no._iterations": 13, "execution_time": 0.107794657, "best_program": "Program([[MoveDown, MoveRight]])", "test_cost": 1, "test_correct": 0, "train_cost": 1, "train_correct": 0, "test_total": 1, "prune_count": 36}, {"complexity": 1, "task": 9, "trial": 1, "no._explored_programs": 1, "best_cost_per_iteration": [[0, 1]], "no._iterations": 13, "execution_time": 0.10738080200000001, "best_program": "Program([[MoveDown, MoveRight]])", "test_cost": 1, "test_correct": 0, "train_cost": 1, "train_correct": 0, "test_total": 1, "prune_count": 36}, {"complexity": 2, "task": 0, "trial": 1, "no._explored_programs": 1, "best_cost_per_iteration": [[0, 1]], "no._iterations": 8, "execution_time": 0.104727981, "best_program": "Program([[MoveDown, Draw]])", "test_cost": 1, "test_correct": 0, "train_cost": 1, "train_correct": 0, "test_total": 1, "prune_count": 36}, {"complexity": 2, "task": 1, "trial": 1, "no._explored_programs": 1, "best_cost_per_iteration": [[0, 1]], "no._iterations": 8, "execution_time": 0.104763443, "best_program": "Program([[MoveDown, Draw]])", "test_cost": 1, "test_correct": 0, "train_cost": 1, "train_correct": 0, "test_total": 1, "prune_count": 36}, {"complexity": 2, "task": 2, "trial": 1, "no._explored_programs": 1, "best_cost_per_iteration": [[0, 1]], "no._iterations": 8, "execution_time": 0.105292468, "best_program": "Program([[MoveDown, Draw]])", "test_cost": 1, "test_correct": 0, "train_cost": 1, "train_correct": 0, "test_total": 1, "prune_count": 36}, {"complexity": 2, "task": 3, "trial": 1, "no._explored_programs": 1, "best_cost_per_iteration": [[0, 1]], "no._iterations": 8, "execution_time": 0.105146769, "best_program": "Program([[MoveDown, Draw]])", "test_cost": 1, "test_correct": 0, "train_cost": 1, "train_correct": 0, "test_total": 1, "prune_count": 36}, {"complexity": 2, "task": 4, "trial": 1, "no._explored_programs": 1, "best_cost_per_iteration": [[0, 1]], "no._iterations": 8, "execution_time": 0.10494658700000001, "best_program": "Program([[MoveDown, Draw]])", "test_cost": 1, "test_correct": 0, "train_cost": 1, "train_correct": 0, "test_total": 1, "prune_count": 36}, {"complexity": 2, "task": 5, "trial": 1, "no._explored_programs": 1, "best_cost_per_iteration": [[0, 1]], "no._iterations": 8, "execution_time": 0.10514501200000001, "best_program": "Program([[MoveDown, Draw]])", "test_cost": 1, "test_correct": 0, "train_cost": 1, "train_correct": 0, "test_total": 1, "prune_count": 36}, {"complexity": 2, "task": 6, "trial": 1, "no._explored_programs": 1, "best_cost_per_iteration": [[0, 1]], "no._iterations": 8, "execution_time": 0.10505653499999999, "best_program": "Program([[MoveDown, Draw]])", "test_cost": 1, "test_correct": 0, "train_cost": 1, "train_correct": 0, "test_total": 1, "prune_count": 36}, {"complexity": 2, "task": 7, "trial": 1, "no._explored_programs": 1, "best_cost_per_iteration": [[0, 1]], "no._iterations": 8, "execution_time": 0.105371971, "best_program": "Program([[MoveDown, Draw]])", "test_cost": 1, "test_correct": 0, "train_cost": 1, "train_correct": 0, "test_total": 1, "prune_count": 36}, {"complexity": 2, "task": 8, "trial": 1, "no._explored_programs": 1, "best_cost_per_iteration": [[0, 1]], "no._iterations": 8, "execution_time": 0.104842003, "best_program": "Program([[MoveDown, Draw]])", "test_cost": 1, "test_correct": 0, "train_cost": 1, "train_correct": 0, "test_total": 1, "prune_count": 36}, {"complexity": 2, "task": 9, "trial": 1, "no._explored_programs": 1, "best_cost_per_iteration": [[0, 1]], "no._iterations": 8, "execution_time": 0.105296575, "best_program": "Program([[MoveDown, Draw]])", "test_cost": 1, "test_correct": 0, "train_cost": 1, "train_correct": 0, "test_total": 1, "prune_count": 36}, {"complexity": 3, "task": 0, "trial": 1, "no._explored_programs": 1, "best_cost_per_iteration": [[0, 1]], "no._iterations": 6, "execution_time": 0.106678056, "best_program": "Program([[Draw, MoveRight]])", "test_cost": 1, "test_correct": 0, "train_cost": 1, "train_correct": 0, "test_total": 1, "prune_count": 36}, {"complexity": 3, "task": 1, "trial": 1, "no._explored_programs": 1, "best_cost_per_iteration": [[0, 1]], "no._iterations": 6, "execution_time": 0.106541503, "best_program": "Program([[Draw, MoveRight]])", "test_cost": 1, "test_correct": 0, "train_cost": 1, "train_correct": 0, "test_total": 1, "prune_count": 36}, {"complexity": 3, "task": 2, "trial": 1, "no._explored_programs": 1, "best_cost_per_iteration": [[0, 1]], "no._iterations": 6, "execution_time": 0.10694415800000001, "best_program": "Program([[Draw, MoveRight]])", "test_cost": 1, "test_correct": 0, "train_cost": 1, "train_correct": 0, "test_total": 1, "prune_count": 36}, {"complexity": 3, "task": 3, "trial": 1, "no._explored_programs": 1, "best_cost_per_iteration": [[0, 1]], "no._iterations": 6, "execution_time": 0.106788667, "best_program": "Program([[Draw, MoveRight]])", "test_cost": 1, "test_correct": 0, "train_cost": 1, "train_correct": 0, "test_total": 1, "prune_count": 36}, {"complexity": 3, "task": 4, "trial": 1, "no._explored_programs": 1, "best_cost_per_iteration": [[0, 1]], "no._iterations": 6, "execution_time": 0.10670079900000001, "best_program": "Program([[Draw, MoveRight]])", "test_cost": 1, "test_correct": 0, "train_cost": 1, "train_correct": 0, "test_total": 1, "prune_count": 36}, {"complexity": 3, "task": 5, "trial": 1, "no._explored_programs": 1, "best_cost_per_iteration": [[0, 1]], "no._iterations": 6, "execution_time": 0.10666020300000001, "best_program": "Program([[Draw, MoveRight]])", "test_cost": 1, "test_correct": 0, "train_cost": 1, "train_correct": 0, "test_total": 1, "prune_count": 36}, {"complexity": 3, "task": 6, "trial": 1, "no._explored_programs": 1, "best_cost_per_iteration": [[0, 1]], "no._iterations": 6, "execution_time": 0.10695321999999999, "best_program": "Program([[Draw, MoveRight]])", "test_cost": 1, "test_correct": 0, "train_cost": 1, "train_correct": 0, "test_total": 1, "prune_count": 36}, {"complexity": 3, "task": 7, "trial": 1, "no._explored_programs": 1, "best_cost_per_iteration": [[0, 1]], "no._iterations": 6, "execution_time": 0.10672727400000001, "best_program": "Program([[Draw, MoveRight]])", "test_cost": 1, "test_correct": 0, "train_cost": 1, "train_correct": 0, "test_total": 1, "prune_count": 36}, {"complexity": 3, "task": 8, "trial": 1, "no._explored_programs": 1, "best_cost_per_iteration": [[0, 1]], "no._iterations": 6, "execution_time": 0.106651877, "best_program": "Program([[Draw, MoveRight]])", "test_cost": 1, "test_correct": 0, "train_cost": 1, "train_correct": 0, "test_total": 1, "prune_count": 36}, {"complexity": 3, "task": 9, "trial": 1, "no._explored_programs": 1, "best_cost_per_iteration": [[0, 1]], "no._iterations": 6, "execution_time": 0.106533477, "best_program": "Program([[Draw, MoveRight]])", "test_cost": 1, "test_correct": 0, "train_cost": 1, "train_correct": 0, "test_total": 1, "prune_count": 36}, {"complexity": 4, "task": 0, "trial": 1, "no._explored_programs": 1, "best_cost_per_iteration": [[0, 1]], "no._iterations": 5, "execution_time": 0.112665374, "best_program": "Program([[MoveDown, MoveDown]])", "test_cost": 1, "test_correct": 0, "train_cost": 1, "train_correct": 0, "test_total": 1, "prune_count": 36}, {"complexity": 4, "task": 1, "trial": 1, "no._explored_programs": 1, "best_cost_per_iteration": [[0, 1]], "no._iterations": 5, "execution_time": 0.112101745, "best_program": "Program([[MoveDown, MoveDown]])", "test_cost": 1, "test_correct": 0, "train_cost": 1, "train_correct": 0, "test_total": 1, "prune_count": 36}, {"complexity": 4, "task": 2, "trial": 1, "no._explored_programs": 1, "best_cost_per_iteration": [[0, 1]], "no._iterations": 5, "execution_time": 0.112435825, "best_program": "Program([[MoveDown, MoveDown]])", "test_cost": 1, "test_correct": 0, "train_cost": 1, "train_correct": 0, "test_total": 1, "prune_count": 36}, {"complexity": 4, "task": 3, "trial": 1, "no._explored_programs": 1, "best_cost_per_iteration": [[0, 1]], "no._iterations": 5, "execution_time": 0.11187880900000001, "best_program": "Program([[MoveDown, MoveDown]])", "test_cost": 1, "test_correct": 0, "train_cost": 1, "train_correct": 0, "test_total": 1, "prune_count": 36}, {"complexity": 4, "task": 4, "trial": 1, "no._explored_programs": 1, "best_cost_per_iteration": [[0, 1]], "no._iterations": 5, "execution_time": 0.11209216000000001, "best_program": "Program([[MoveDown, MoveDown]])", "test_cost": 1, "test_correct": 0, "train_cost": 1, "train_correct": 0, "test_total": 1, "prune_count": 36}, {"complexity": 4, "task": 5, "trial": 1, "no._explored_programs": 1, "best_cost_per_iteration": [[0, 1]], "no._iterations": 5, "execution_time": 0.112474292, "best_program": "Program([[MoveDown, MoveDown]])", "test_cost": 1, "test_correct": 0, "train_cost": 1, "train_correct": 0, "test_total": 1, "prune_count": 36}, {"complexity": 4, "task": 6, "trial": 1, "no._explored_programs": 1, "best_cost_per_iteration": [[0, 1]], "no._iterations": 5, "execution_time": 0.112036626, "best_program": "Program([[MoveDown, MoveDown]])", "test_cost": 1, "test_correct": 0, "train_cost": 1, "train_correct": 0, "test_total": 1, "prune_count": 36}, {"complexity": 4, "task": 7, "trial": 1, "no._explored_programs": 1, "best_cost_per_iteration": [[0, 1]], "no._iterations": 5, "execution_time": 0.112132795, "best_program": "Program([[MoveDown, MoveDown]])", "test_cost": 1, "test_correct": 0, "train_cost": 1, "train_correct": 0, "test_total": 1, "prune_count": 36}, {"complexity": 4, "task": 8, "trial": 1, "no._explored_programs": 1, "best_cost_per_iteration": [[0, 1]], "no._iterations": 5, "execution_time": 0.11200885099999999, "best_program": "Program([[MoveDown, MoveDown]])", "test_cost": 1, "test_correct": 0, "train_cost": 1, "train_correct": 0, "test_total": 1, "prune_count": 36}, {"complexity": 4, "task": 9, "trial": 1, "no._explored_programs": 1, "best_cost_per_iteration": [[0, 1]], "no._iterations": 5, "execution_time": 0.11218334499999999, "best_program": "Program([[MoveDown, MoveDown]])", "test_cost": 1, "test_correct": 0, "train_cost": 1, "train_correct": 0, "test_total": 1, "prune_count": 36}, {"complexity": 5, "task": 0, "trial": 1, "no._explored_programs": 1, "best_cost_per_iteration": [[0, 1]], "no._iterations": 4, "execution_time": 0.105628206, "best_program": "Program([[MoveDown]])", "test_cost": 1, "test_correct": 0, "train_cost": 1, "train_correct": 0, "test_total": 1, "prune_count": 36}, {"complexity": 5, "task": 1, "trial": 1, "no._explored_programs": 1, "best_cost_per_iteration": [[0, 1]], "no._iterations": 4, "execution_time": 0.105862082, "best_program": "Program([[MoveDown]])", "test_cost": 1, "test_correct": 0, "train_cost": 1, "train_correct": 0, "test_total": 1, "prune_count": 36}, {"complexity": 5, "task": 2, "trial": 1, "no._explored_programs": 1, "best_cost_per_iteration": [[0, 1]], "no._iterations": 4, "execution_time": 0.105411697, "best_program": "Program([[MoveDown]])", "test_cost": 1, "test_correct": 0, "train_cost": 1, "train_correct": 0, "test_total": 1, "prune_count": 36}, {"complexity": 5, "task": 3, "trial": 1, "no._explored_programs": 1, "best_cost_per_iteration": [[0, 1]], "no._iterations": 4, "execution_time": 0.105564888, "best_program": "Program([[MoveDown]])", "test_cost": 1, "test_correct": 0, "train_cost": 1, "train_correct": 0, "test_total": 1, "prune_count": 36}, {"complexity": 5, "task": 4, "trial": 1, "no._explored_programs": 1, "best_cost_per_iteration": [[0, 1]], "no._iterations": 4, "execution_time": 0.10520550299999999, "best_program": "Program([[MoveDown]])", "test_cost": 1, "test_correct": 0, "train_cost": 1, "train_correct": 0, "test_total": 1, "prune_count": 36}, {"complexity": 5, "task": 5, "trial": 1, "no._explored_programs": 1, "best_cost_per_iteration": [[0, 1]], "no._iterations": 4, "execution_time": 0.105331009, "best_program": "Program([[MoveDown]])", "test_cost": 1, "test_correct": 0, "train_cost": 1, "train_correct": 0, "test_total": 1, "prune_count": 36}, {"complexity": 5, "task": 6, "trial": 1, "no._explored_programs": 1, "best_cost_per_iteration": [[0, 1]], "no._iterations": 4, "execution_time": 0.105321501, "best_program": "Program([[MoveDown]])", "test_cost": 1, "test_correct": 0, "train_cost": 1, "train_correct": 0, "test_total": 1, "prune_count": 36}, {"complexity": 5, "task": 7, "trial": 1, "no._explored_programs": 1, "best_cost_per_iteration": [[0, 1]], "no._iterations": 4, "execution_time": 0.10398313000000001, "best_program": "Program([[MoveDown]])", "test_cost": 1, "test_correct": 0, "train_cost": 1, "train_correct": 0, "test_total": 1, "prune_count": 36}, {"complexity": 5, "task": 8, "trial": 1, "no._explored_programs": 1, "best_cost_per_iteration": [[0, 1]], "no._iterations": 4, "execution_time": 0.104049961, "best_program": "Program([[MoveDown]])", "test_cost": 1, "test_correct": 0, "train_cost": 1, "train_correct": 0, "test_total": 1, "prune_count": 36}, {"complexity": 5, "task": 9, "trial": 1, "no._explored_programs": 1, "best_cost_per_iteration": [[0, 1]], "no._iterations": 4, "execution_time": 0.104345322, "best_program": "Program([[MoveDown]])", "test_cost": 1, "test_correct": 0, "train_cost": 1, "train_correct": 0, "test_total": 1, "prune_count": 36}]]