[[{"complexity": 1, "task": 0, "trial": 1, "no._explored_programs": 1, "best_cost_per_iteration": [[0, 1]], "no._iterations": 13, "execution_time": 0.107991872, "best_program": "Program([[MoveRight, Draw]])", "test_cost": 1, "test_correct": 0, "train_cost": 1, "train_correct": 0, "test_total": 1, "prune_count": 36}, {"complexity": 1, "task": 1, "trial": 1, "no._explored_programs": 1, "best_cost_per_iteration": [[0, 1]], "no._iterations": 13, "execution_time": 0.107997021, "best_program": "Program([[MoveRight, Draw]])", "test_cost": 1, "test_correct": 0, "train_cost": 1, "train_correct": 0, "test_total": 1, "prune_count": 36}, {"complexity": 1, "task": 2, "trial": 1, "no._explored_programs": 1, "best_cost_per_iteration": [[0, 1]], "no._iterations": 13, "execution_time": 0.107675571, "best_program": "Program([[MoveRight, Draw]])", "test_cost": 1, "test_correct": 0, "train_cost": 1, "train_correct": 0, "test_total": 1, "prune_count": 36}, {"complexity": 1, "task": 3, "trial": 1, "no._explored_programs": 1, "best_cost_per_iteration": [[0, 1]], "no._iterations": 13, "execution_time": 0.10725037300000001, "best_program": "Program([[MoveRight, Draw]])", "test_cost": 1, "test_correct": 0, "train_cost": 1, "train_correct": 0, "test_total": 1, "prune_count": 36}, {"complexity": 1, "task": 4, "trial": 1, "no._explored_programs": 1, "best_cost_per_iteration": [[0, 1]], "no._iterations": 13, "execution_time": 0.10774833, "best_program": "Program([[MoveRight, Draw]])", "test_cost": 1, "test_correct": 0, "train_cost": 1, "train_correct": 0, "test_total": 1, "prune_count": 36}, {"complexity": 1, "task": 5, "trial": 1, "no._explored_programs": 1, "best_cost_per_iteration": [[0, 1]], "no._iterations": 12, "execution_time": 0.10003547500000001, "best_program": "Program([LoopWhileThen(NotAtRight [MoveRight], [MoveDown])])", "test_cost": 1, "test_correct": 0, "train_cost": 1, "train_correct": 0, "test_total": 1, "prune_count": 36}, {"complexity": 1, "task": 6, "trial": 1, "no._explored_programs": 1, "best_cost_per_iteration": [[0, 1]], "no._iterations": 13, "execution_time": 0.108287518, "best_program": "Program([[MoveRight, Draw]])", "test_cost": 1, "test_correct": 0, "train_cost": 1, "train_correct": 0, "test_total": 1, "prune_count": 36}, {"complexity": 1, "task": 7, "trial": 1, "no._explored_programs": 1, "best_cost_per_iteration": [[0, 1]], "no._iterations": 13, "execution_time": 0.107978269, "best_program": "Program([[MoveRight, Draw]])", "test_cost": 1, "test_correct": 0, "train_cost": 1, "train_correct": 0, "test_total": 1, "prune_count": 36}, {"complexity": 1, "task": 8, "trial": 1, "no._explored_programs": 1, "best_cost_per_iteration": [[0, 1]], "no._iterations": 13, "execution_time": 0.10657166099999998, "best_program": "Program([[MoveRight, Draw]])", "test_cost": 1, "test_correct": 0, "train_cost": 1, "train_correct": 0, "test_total": 1, "prune_count": 36}, {"complexity": 1, "task": 9, "trial": 1, "no._explored_programs": 1, "best_cost_per_iteration": [[0, 1]], "no._iterations": 13, "execution_time": 0.10797372100000001, "best_program": "Program([[MoveRight, Draw]])", "test_cost": 1, "test_correct": 0, "train_cost": 1, "train_correct": 0, "test_total": 1, "prune_count": 36}, {"complexity": 2, "task": 0, "trial": 1, "no._explored_programs": 1, "best_cost_per_iteration": [[0, 1]], "no._iterations": 8, "execution_time": 0.106604244, "best_program": "Program([[MoveDown, Draw]])", "test_cost": 1, "test_correct": 0, "train_cost": 1, "train_correct": 0, "test_total": 1, "prune_count": 36}, {"complexity": 2, "task": 1, "trial": 1, "no._explored_programs": 1, "best_cost_per_iteration": [[0, 1]], "no._iterations": 8, "execution_time": 0.106426362, "best_program": "Program([[MoveDown, Draw]])", "test_cost": 1, "test_correct": 0, "train_cost": 1, "train_correct": 0, "test_total": 1, "prune_count": 36}, {"complexity": 2, "task": 2, "trial": 1, "no._explored_programs": 1, "best_cost_per_iteration": [[0, 1]], "no._iterations": 8, "execution_time": 0.106476203, "best_program": "Program([[MoveDown, Draw]])", "test_cost": 1, "test_correct": 0, "train_cost": 1, "train_correct": 0, "test_total": 1, "prune_count": 36}, {"complexity": 2, "task": 3, "trial": 1, "no._explored_programs": 1, "best_cost_per_iteration": [[0, 1]], "no._iterations": 8, "execution_time": 0.106377735, "best_program": "Program([[MoveDown, Draw]])", "test_cost": 1, "test_correct": 0, "train_cost": 1, "train_correct": 0, "test_total": 1, "prune_count": 36}, {"complexity": 2, "task": 4, "trial": 1, "no._explored_programs": 1, "best_cost_per_iteration": [[0, 1]], "no._iterations": 8, "execution_time": 0.10643628299999999, "best_program": "Program([[MoveDown, Draw]])", "test_cost": 1, "test_correct": 0, "train_cost": 1, "train_correct": 0, "test_total": 1, "prune_count": 36}, {"complexity": 2, "task": 5, "trial": 1, "no._explored_programs": 1, "best_cost_per_iteration": [[0, 1]], "no._iterations": 8, "execution_time": 0.106372253, "best_program": "Program([[MoveDown, Draw]])", "test_cost": 1, "test_correct": 0, "train_cost": 1, "train_correct": 0, "test_total": 1, "prune_count": 36}, {"complexity": 2, "task": 6, "trial": 1, "no._explored_programs": 1, "best_cost_per_iteration": [[0, 1]], "no._iterations": 8, "execution_time": 0.106364004, "best_program": "Program([[MoveDown, Draw]])", "test_cost": 1, "test_correct": 0, "train_cost": 1, "train_correct": 0, "test_total": 1, "prune_count": 36}, {"complexity": 2, "task": 7, "trial": 1, "no._explored_programs": 1, "best_cost_per_iteration": [[0, 1]], "no._iterations": 8, "execution_time": 0.106232937, "best_program": "Program([[MoveDown, Draw]])", "test_cost": 1, "test_correct": 0, "train_cost": 1, "train_correct": 0, "test_total": 1, "prune_count": 36}, {"complexity": 2, "task": 8, "trial": 1, "no._explored_programs": 1, "best_cost_per_iteration": [[0, 1]], "no._iterations": 8, "execution_time": 0.105058692, "best_program": "Program([[MoveDown, Draw]])", "test_cost": 1, "test_correct": 0, "train_cost": 1, "train_correct": 0, "test_total": 1, "prune_count": 36}, {"complexity": 2, "task": 9, "trial": 1, "no._explored_programs": 1, "best_cost_per_iteration": [[0, 1]], "no._iterations": 8, "execution_time": 0.106429488, "best_program": "Program([[MoveDown, Draw]])", "test_cost": 1, "test_correct": 0, "train_cost": 1, "train_correct": 0, "test_total": 1, "prune_count": 36}, {"complexity": 3, "task": 0, "trial": 1, "no._explored_programs": 1, "best_cost_per_iteration": [[0, 1]], "no._iterations": 6, "execution_time": 0.10672674200000001, "best_program": "Program([[Draw, MoveRight]])", "test_cost": 1, "test_correct": 0, "train_cost": 1, "train_correct": 0, "test_total": 1, "prune_count": 36}, {"complexity": 3, "task": 1, "trial": 1, "no._explored_programs": 1, "best_cost_per_iteration": [[0, 1]], "no._iterations": 6, "execution_time": 0.108492702, "best_program": "Program([[Draw, MoveRight]])", "test_cost": 1, "test_correct": 0, "train_cost": 1, "train_correct": 0, "test_total": 1, "prune_count": 36}, {"complexity": 3, "task": 2, "trial": 1, "no._explored_programs": 1, "best_cost_per_iteration": [[0, 1]], "no._iterations": 6, "execution_time": 0.107987735, "best_program": "Program([[Draw, MoveRight]])", "test_cost": 1, "test_correct": 0, "train_cost": 1, "train_correct": 0, "test_total": 1, "prune_count": 36}, {"complexity": 3, "task": 3, "trial": 1, "no._explored_programs": 1, "best_cost_per_iteration": [[0, 1]], "no._iterations": 6, "execution_time": 0.10726310999999998, "best_program": "Program([[Draw, MoveRight]])", "test_cost": 1, "test_correct": 0, "train_cost": 1, "train_correct": 0, "test_total": 1, "prune_count": 36}, {"complexity": 3, "task": 4, "trial": 1, "no._explored_programs": 1, "best_cost_per_iteration": [[0, 1]], "no._iterations": 6, "execution_time": 0.108352315, "best_program": "Program([[Draw, MoveRight]])", "test_cost": 1, "test_correct": 0, "train_cost": 1, "train_correct": 0, "test_total": 1, "prune_count": 36}, {"complexity": 3, "task": 5, "trial": 1, "no._explored_programs": 1, "best_cost_per_iteration": [[0, 1]], "no._iterations": 6, "execution_time": 0.10832800499999999, "best_program": "Program([[Draw, MoveRight]])", "test_cost": 1, "test_correct": 0, "train_cost": 1, "train_correct": 0, "test_total": 1, "prune_count": 36}, {"complexity": 3, "task": 6, "trial": 1, "no._explored_programs": 1, "best_cost_per_iteration": [[0, 1]], "no._iterations": 6, "execution_time": 0.10723611699999999, "best_program": "Program([[Draw, MoveRight]])", "test_cost": 1, "test_correct": 0, "train_cost": 1, "train_correct": 0, "test_total": 1, "prune_count": 36}, {"complexity": 3, "task": 7, "trial": 1, "no._explored_programs": 1, "best_cost_per_iteration": [[0, 1]], "no._iterations": 6, "execution_time": 0.10708471400000001, "best_program": "Program([[Draw, MoveRight]])", "test_cost": 1, "test_correct": 0, "train_cost": 1, "train_correct": 0, "test_total": 1, "prune_count": 36}, {"complexity": 3, "task": 8, "trial": 1, "no._explored_programs": 1, "best_cost_per_iteration": [[0, 1]], "no._iterations": 6, "execution_time": 0.109974485, "best_program": "Program([[Draw, MoveRight]])", "test_cost": 1, "test_correct": 0, "train_cost": 1, "train_correct": 0, "test_total": 1, "prune_count": 36}, {"complexity": 3, "task": 9, "trial": 1, "no._explored_programs": 1, "best_cost_per_iteration": [[0, 1]], "no._iterations": 6, "execution_time": 0.10712358100000002, "best_program": "Program([[Draw, MoveRight]])", "test_cost": 1, "test_correct": 0, "train_cost": 1, "train_correct": 0, "test_total": 1, "prune_count": 36}, {"complexity": 4, "task": 0, "trial": 1, "no._explored_programs": 1, "best_cost_per_iteration": [[0, 1]], "no._iterations": 5, "execution_time": 0.115074467, "best_program": "Program([LoopWhileThen(NotAtRight [MoveRight], [MoveLeft])])", "test_cost": 1, "test_correct": 0, "train_cost": 1, "train_correct": 0, "test_total": 1, "prune_count": 36}, {"complexity": 4, "task": 1, "trial": 1, "no._explored_programs": 1, "best_cost_per_iteration": [[0, 1]], "no._iterations": 5, "execution_time": 0.112425972, "best_program": "Program([LoopWhileThen(NotAtRight [MoveRight], [MoveLeft])])", "test_cost": 1, "test_correct": 0, "train_cost": 1, "train_correct": 0, "test_total": 1, "prune_count": 36}, {"complexity": 4, "task": 2, "trial": 1, "no._explored_programs": 1, "best_cost_per_iteration": [[0, 1]], "no._iterations": 5, "execution_time": 0.112395805, "best_program": "Program([LoopWhileThen(NotAtRight [MoveRight], [MoveLeft])])", "test_cost": 1, "test_correct": 0, "train_cost": 1, "train_correct": 0, "test_total": 1, "prune_count": 36}, {"complexity": 4, "task": 3, "trial": 1, "no._explored_programs": 1, "best_cost_per_iteration": [[0, 1]], "no._iterations": 5, "execution_time": 0.11398596899999999, "best_program": "Program([LoopWhileThen(NotAtRight [MoveRight], [MoveLeft])])", "test_cost": 1, "test_correct": 0, "train_cost": 1, "train_correct": 0, "test_total": 1, "prune_count": 36}, {"complexity": 4, "task": 4, "trial": 1, "no._explored_programs": 1, "best_cost_per_iteration": [[0, 1]], "no._iterations": 5, "execution_time": 0.113965487, "best_program": "Program([LoopWhileThen(NotAtRight [MoveRight], [MoveLeft])])", "test_cost": 1, "test_correct": 0, "train_cost": 1, "train_correct": 0, "test_total": 1, "prune_count": 36}, {"complexity": 4, "task": 5, "trial": 1, "no._explored_programs": 1, "best_cost_per_iteration": [[0, 1]], "no._iterations": 5, "execution_time": 0.11393419799999999, "best_program": "Program([LoopWhileThen(NotAtRight [MoveRight], [MoveLeft])])", "test_cost": 1, "test_correct": 0, "train_cost": 1, "train_correct": 0, "test_total": 1, "prune_count": 36}, {"complexity": 4, "task": 6, "trial": 1, "no._explored_programs": 1, "best_cost_per_iteration": [[0, 1]], "no._iterations": 5, "execution_time": 0.113807535, "best_program": "Program([LoopWhileThen(NotAtRight [MoveRight], [MoveLeft])])", "test_cost": 1, "test_correct": 0, "train_cost": 1, "train_correct": 0, "test_total": 1, "prune_count": 36}, {"complexity": 4, "task": 7, "trial": 1, "no._explored_programs": 1, "best_cost_per_iteration": [[0, 1]], "no._iterations": 5, "execution_time": 0.11390230600000001, "best_program": "Program([LoopWhileThen(NotAtRight [MoveRight], [MoveLeft])])", "test_cost": 1, "test_correct": 0, "train_cost": 1, "train_correct": 0, "test_total": 1, "prune_count": 36}, {"complexity": 4, "task": 8, "trial": 1, "no._explored_programs": 1, "best_cost_per_iteration": [[0, 1]], "no._iterations": 5, "execution_time": 0.11421574400000001, "best_program": "Program([LoopWhileThen(NotAtRight [MoveRight], [MoveLeft])])", "test_cost": 1, "test_correct": 0, "train_cost": 1, "train_correct": 0, "test_total": 1, "prune_count": 36}, {"complexity": 4, "task": 9, "trial": 1, "no._explored_programs": 1, "best_cost_per_iteration": [[0, 1]], "no._iterations": 5, "execution_time": 0.11383863500000001, "best_program": "Program([LoopWhileThen(NotAtRight [MoveRight], [MoveLeft])])", "test_cost": 1, "test_correct": 0, "train_cost": 1, "train_correct": 0, "test_total": 1, "prune_count": 36}, {"complexity": 5, "task": 0, "trial": 1, "no._explored_programs": 1, "best_cost_per_iteration": [[0, 1]], "no._iterations": 4, "execution_time": 0.106929308, "best_program": "Program([[MoveDown]])", "test_cost": 1, "test_correct": 0, "train_cost": 1, "train_correct": 0, "test_total": 1, "prune_count": 36}, {"complexity": 5, "task": 1, "trial": 1, "no._explored_programs": 1, "best_cost_per_iteration": [[0, 1]], "no._iterations": 4, "execution_time": 0.106748724, "best_program": "Program([[MoveDown]])", "test_cost": 1, "test_correct": 0, "train_cost": 1, "train_correct": 0, "test_total": 1, "prune_count": 36}, {"complexity": 5, "task": 2, "trial": 1, "no._explored_programs": 1, "best_cost_per_iteration": [[0, 1]], "no._iterations": 4, "execution_time": 0.107266345, "best_program": "Program([[MoveDown]])", "test_cost": 1, "test_correct": 0, "train_cost": 1, "train_correct": 0, "test_total": 1, "prune_count": 36}, {"complexity": 5, "task": 3, "trial": 1, "no._explored_programs": 1, "best_cost_per_iteration": [[0, 1]], "no._iterations": 4, "execution_time": 0.10575682599999998, "best_program": "Program([[MoveDown]])", "test_cost": 1, "test_correct": 0, "train_cost": 1, "train_correct": 0, "test_total": 1, "prune_count": 36}, {"complexity": 5, "task": 4, "trial": 1, "no._explored_programs": 1, "best_cost_per_iteration": [[0, 1]], "no._iterations": 4, "execution_time": 0.105452766, "best_program": "Program([[MoveDown]])", "test_cost": 1, "test_correct": 0, "train_cost": 1, "train_correct": 0, "test_total": 1, "prune_count": 36}, {"complexity": 5, "task": 5, "trial": 1, "no._explored_programs": 1, "best_cost_per_iteration": [[0, 1]], "no._iterations": 4, "execution_time": 0.106729772, "best_program": "Program([[MoveDown]])", "test_cost": 1, "test_correct": 0, "train_cost": 1, "train_correct": 0, "test_total": 1, "prune_count": 36}, {"complexity": 5, "task": 6, "trial": 1, "no._explored_programs": 1, "best_cost_per_iteration": [[0, 1]], "no._iterations": 4, "execution_time": 0.106777918, "best_program": "Program([[MoveDown]])", "test_cost": 1, "test_correct": 0, "train_cost": 1, "train_correct": 0, "test_total": 1, "prune_count": 36}, {"complexity": 5, "task": 7, "trial": 1, "no._explored_programs": 1, "best_cost_per_iteration": [[0, 1]], "no._iterations": 4, "execution_time": 0.106712993, "best_program": "Program([[MoveDown]])", "test_cost": 1, "test_correct": 0, "train_cost": 1, "train_correct": 0, "test_total": 1, "prune_count": 36}, {"complexity": 5, "task": 8, "trial": 1, "no._explored_programs": 1, "best_cost_per_iteration": [[0, 1]], "no._iterations": 4, "execution_time": 0.10527295, "best_program": "Program([[MoveDown]])", "test_cost": 1, "test_correct": 0, "train_cost": 1, "train_correct": 0, "test_total": 1, "prune_count": 36}, {"complexity": 5, "task": 9, "trial": 1, "no._explored_programs": 1, "best_cost_per_iteration": [[0, 1]], "no._iterations": 4, "execution_time": 0.10666711, "best_program": "Program([[MoveDown]])", "test_cost": 1, "test_correct": 0, "train_cost": 1, "train_correct": 0, "test_total": 1, "prune_count": 36}]]