[[{"complexity": 1, "task": 0, "trial": 1, "no._explored_programs": 1, "best_cost_per_iteration": [[0, 1]], "no._iterations": 13, "execution_time": 0.10072738, "best_program": "Program([[MoveDown, MoveRight]])", "test_cost": 1, "test_correct": 0, "train_cost": 1, "train_correct": 0, "test_total": 1, "prune_count": 63}, {"complexity": 1, "task": 1, "trial": 1, "no._explored_programs": 1, "best_cost_per_iteration": [[0, 1]], "no._iterations": 14, "execution_time": 0.105569549, "best_program": "Program([[MoveDown, MoveDown]])", "test_cost": 1, "test_correct": 0, "train_cost": 1, "train_correct": 0, "test_total": 1, "prune_count": 63}, {"complexity": 1, "task": 2, "trial": 1, "no._explored_programs": 1, "best_cost_per_iteration": [[0, 1]], "no._iterations": 14, "execution_time": 0.10565888699999999, "best_program": "Program([[MoveDown, MoveDown]])", "test_cost": 1, "test_correct": 0, "train_cost": 1, "train_correct": 0, "test_total": 1, "prune_count": 63}, {"complexity": 1, "task": 3, "trial": 1, "no._explored_programs": 1, "best_cost_per_iteration": [[0, 1]], "no._iterations": 14, "execution_time": 0.10496987400000002, "best_program": "Program([[MoveDown, MoveDown]])", "test_cost": 1, "test_correct": 0, "train_cost": 1, "train_correct": 0, "test_total": 1, "prune_count": 63}, {"complexity": 1, "task": 4, "trial": 1, "no._explored_programs": 1, "best_cost_per_iteration": [[0, 1]], "no._iterations": 14, "execution_time": 0.106113272, "best_program": "Program([[MoveDown, MoveDown]])", "test_cost": 1, "test_correct": 0, "train_cost": 1, "train_correct": 0, "test_total": 1, "prune_count": 63}, {"complexity": 1, "task": 5, "trial": 1, "no._explored_programs": 1, "best_cost_per_iteration": [[0, 1]], "no._iterations": 14, "execution_time": 0.105590023, "best_program": "Program([[MoveDown, MoveDown]])", "test_cost": 1, "test_correct": 0, "train_cost": 1, "train_correct": 0, "test_total": 1, "prune_count": 63}, {"complexity": 1, "task": 6, "trial": 1, "no._explored_programs": 1, "best_cost_per_iteration": [[0, 1]], "no._iterations": 14, "execution_time": 0.105572105, "best_program": "Program([[MoveDown, MoveDown]])", "test_cost": 1, "test_correct": 0, "train_cost": 1, "train_correct": 0, "test_total": 1, "prune_count": 63}, {"complexity": 1, "task": 7, "trial": 1, "no._explored_programs": 1, "best_cost_per_iteration": [[0, 1]], "no._iterations": 14, "execution_time": 0.10571808199999999, "best_program": "Program([[MoveDown, MoveDown]])", "test_cost": 1, "test_correct": 0, "train_cost": 1, "train_correct": 0, "test_total": 1, "prune_count": 63}, {"complexity": 1, "task": 8, "trial": 1, "no._explored_programs": 1, "best_cost_per_iteration": [[0, 1]], "no._iterations": 14, "execution_time": 0.10483287599999999, "best_program": "Program([[MoveDown, MoveDown]])", "test_cost": 1, "test_correct": 0, "train_cost": 1, "train_correct": 0, "test_total": 1, "prune_count": 63}, {"complexity": 1, "task": 9, "trial": 1, "no._explored_programs": 1, "best_cost_per_iteration": [[0, 1]], "no._iterations": 14, "execution_time": 0.10520792799999999, "best_program": "Program([[MoveDown, MoveDown]])", "test_cost": 1, "test_correct": 0, "train_cost": 1, "train_correct": 0, "test_total": 1, "prune_count": 63}, {"complexity": 2, "task": 0, "trial": 1, "no._explored_programs": 1, "best_cost_per_iteration": [[0, 1]], "no._iterations": 9, "execution_time": 0.108490766, "best_program": "Program([LoopWhileThen(NotAtBottom [MoveDown], [MoveRight])])", "test_cost": 1, "test_correct": 0, "train_cost": 1, "train_correct": 0, "test_total": 1, "prune_count": 63}, {"complexity": 2, "task": 1, "trial": 1, "no._explored_programs": 1, "best_cost_per_iteration": [[0, 1]], "no._iterations": 9, "execution_time": 0.10682550500000002, "best_program": "Program([LoopWhileThen(NotAtBottom [MoveDown], [MoveRight])])", "test_cost": 1, "test_correct": 0, "train_cost": 1, "train_correct": 0, "test_total": 1, "prune_count": 63}, {"complexity": 2, "task": 2, "trial": 1, "no._explored_programs": 1, "best_cost_per_iteration": [[0, 1]], "no._iterations": 9, "execution_time": 0.108352825, "best_program": "Program([LoopWhileThen(NotAtBottom [MoveDown], [MoveRight])])", "test_cost": 1, "test_correct": 0, "train_cost": 1, "train_correct": 0, "test_total": 1, "prune_count": 63}, {"complexity": 2, "task": 3, "trial": 1, "no._explored_programs": 1, "best_cost_per_iteration": [[0, 1]], "no._iterations": 9, "execution_time": 0.107669452, "best_program": "Program([LoopWhileThen(NotAtBottom [MoveDown], [MoveRight])])", "test_cost": 1, "test_correct": 0, "train_cost": 1, "train_correct": 0, "test_total": 1, "prune_count": 63}, {"complexity": 2, "task": 4, "trial": 1, "no._explored_programs": 1, "best_cost_per_iteration": [[0, 1]], "no._iterations": 9, "execution_time": 0.106727818, "best_program": "Program([LoopWhileThen(NotAtBottom [MoveDown], [MoveRight])])", "test_cost": 1, "test_correct": 0, "train_cost": 1, "train_correct": 0, "test_total": 1, "prune_count": 63}, {"complexity": 2, "task": 5, "trial": 1, "no._explored_programs": 1, "best_cost_per_iteration": [[0, 1]], "no._iterations": 9, "execution_time": 0.10932755300000001, "best_program": "Program([LoopWhileThen(NotAtBottom [MoveDown], [MoveRight])])", "test_cost": 1, "test_correct": 0, "train_cost": 1, "train_correct": 0, "test_total": 1, "prune_count": 63}, {"complexity": 2, "task": 6, "trial": 1, "no._explored_programs": 1, "best_cost_per_iteration": [[0, 1]], "no._iterations": 9, "execution_time": 0.107546899, "best_program": "Program([LoopWhileThen(NotAtBottom [MoveDown], [MoveRight])])", "test_cost": 1, "test_correct": 0, "train_cost": 1, "train_correct": 0, "test_total": 1, "prune_count": 63}, {"complexity": 2, "task": 7, "trial": 1, "no._explored_programs": 1, "best_cost_per_iteration": [[0, 1]], "no._iterations": 9, "execution_time": 0.10711293300000002, "best_program": "Program([LoopWhileThen(NotAtBottom [MoveDown], [MoveRight])])", "test_cost": 1, "test_correct": 0, "train_cost": 1, "train_correct": 0, "test_total": 1, "prune_count": 63}, {"complexity": 2, "task": 8, "trial": 1, "no._explored_programs": 1, "best_cost_per_iteration": [[0, 1]], "no._iterations": 9, "execution_time": 0.10792004, "best_program": "Program([LoopWhileThen(NotAtBottom [MoveDown], [MoveRight])])", "test_cost": 1, "test_correct": 0, "train_cost": 1, "train_correct": 0, "test_total": 1, "prune_count": 63}, {"complexity": 2, "task": 9, "trial": 1, "no._explored_programs": 1, "best_cost_per_iteration": [[0, 1]], "no._iterations": 9, "execution_time": 0.108541426, "best_program": "Program([LoopWhileThen(NotAtBottom [MoveDown], [MoveRight])])", "test_cost": 1, "test_correct": 0, "train_cost": 1, "train_correct": 0, "test_total": 1, "prune_count": 63}, {"complexity": 3, "task": 0, "trial": 1, "no._explored_programs": 1, "best_cost_per_iteration": [[0, 1]], "no._iterations": 7, "execution_time": 0.113145304, "best_program": "Program([[MoveRight, MoveRight]])", "test_cost": 1, "test_correct": 0, "train_cost": 1, "train_correct": 0, "test_total": 1, "prune_count": 63}, {"complexity": 3, "task": 1, "trial": 1, "no._explored_programs": 1, "best_cost_per_iteration": [[0, 1]], "no._iterations": 7, "execution_time": 0.11544653299999999, "best_program": "Program([[MoveRight, MoveRight]])", "test_cost": 1, "test_correct": 0, "train_cost": 1, "train_correct": 0, "test_total": 1, "prune_count": 63}, {"complexity": 3, "task": 2, "trial": 1, "no._explored_programs": 1, "best_cost_per_iteration": [[0, 1]], "no._iterations": 7, "execution_time": 0.11645578499999999, "best_program": "Program([[MoveRight, MoveRight]])", "test_cost": 1, "test_correct": 0, "train_cost": 1, "train_correct": 0, "test_total": 1, "prune_count": 63}, {"complexity": 3, "task": 3, "trial": 1, "no._explored_programs": 1, "best_cost_per_iteration": [[0, 1]], "no._iterations": 7, "execution_time": 0.116520711, "best_program": "Program([[MoveRight, MoveRight]])", "test_cost": 1, "test_correct": 0, "train_cost": 1, "train_correct": 0, "test_total": 1, "prune_count": 63}, {"complexity": 3, "task": 4, "trial": 1, "no._explored_programs": 1, "best_cost_per_iteration": [[0, 1]], "no._iterations": 7, "execution_time": 0.11286304000000003, "best_program": "Program([[MoveRight, MoveRight]])", "test_cost": 1, "test_correct": 0, "train_cost": 1, "train_correct": 0, "test_total": 1, "prune_count": 63}, {"complexity": 3, "task": 5, "trial": 1, "no._explored_programs": 1, "best_cost_per_iteration": [[0, 1]], "no._iterations": 7, "execution_time": 0.11560200899999999, "best_program": "Program([[MoveRight, MoveRight]])", "test_cost": 1, "test_correct": 0, "train_cost": 1, "train_correct": 0, "test_total": 1, "prune_count": 63}, {"complexity": 3, "task": 6, "trial": 1, "no._explored_programs": 1, "best_cost_per_iteration": [[0, 1]], "no._iterations": 7, "execution_time": 0.114449135, "best_program": "Program([[MoveRight, MoveRight]])", "test_cost": 1, "test_correct": 0, "train_cost": 1, "train_correct": 0, "test_total": 1, "prune_count": 63}, {"complexity": 3, "task": 7, "trial": 1, "no._explored_programs": 1, "best_cost_per_iteration": [[0, 1]], "no._iterations": 7, "execution_time": 0.11465205800000003, "best_program": "Program([[MoveRight, MoveRight]])", "test_cost": 1, "test_correct": 0, "train_cost": 1, "train_correct": 0, "test_total": 1, "prune_count": 63}, {"complexity": 3, "task": 8, "trial": 1, "no._explored_programs": 1, "best_cost_per_iteration": [[0, 1]], "no._iterations": 7, "execution_time": 0.115848062, "best_program": "Program([[MoveRight, MoveRight]])", "test_cost": 1, "test_correct": 0, "train_cost": 1, "train_correct": 0, "test_total": 1, "prune_count": 63}, {"complexity": 3, "task": 9, "trial": 1, "no._explored_programs": 1, "best_cost_per_iteration": [[0, 1]], "no._iterations": 7, "execution_time": 0.11444182900000001, "best_program": "Program([[MoveRight, MoveRight]])", "test_cost": 1, "test_correct": 0, "train_cost": 1, "train_correct": 0, "test_total": 1, "prune_count": 63}, {"complexity": 4, "task": 0, "trial": 1, "no._explored_programs": 1, "best_cost_per_iteration": [[0, 1]], "no._iterations": 5, "execution_time": 0.10147884700000001, "best_program": "Program([LoopWhileThen(NotAtBottom [MoveDown], [Draw])])", "test_cost": 1, "test_correct": 0, "train_cost": 1, "train_correct": 0, "test_total": 1, "prune_count": 63}, {"complexity": 4, "task": 1, "trial": 1, "no._explored_programs": 1, "best_cost_per_iteration": [[0, 1]], "no._iterations": 5, "execution_time": 0.10184174, "best_program": "Program([LoopWhileThen(NotAtBottom [MoveDown], [Draw])])", "test_cost": 1, "test_correct": 0, "train_cost": 1, "train_correct": 0, "test_total": 1, "prune_count": 63}, {"complexity": 4, "task": 2, "trial": 1, "no._explored_programs": 1, "best_cost_per_iteration": [[0, 1]], "no._iterations": 5, "execution_time": 0.10137174399999999, "best_program": "Program([LoopWhileThen(NotAtBottom [MoveDown], [Draw])])", "test_cost": 1, "test_correct": 0, "train_cost": 1, "train_correct": 0, "test_total": 1, "prune_count": 63}, {"complexity": 4, "task": 3, "trial": 1, "no._explored_programs": 1, "best_cost_per_iteration": [[0, 1]], "no._iterations": 5, "execution_time": 0.102266815, "best_program": "Program([LoopWhileThen(NotAtBottom [MoveDown], [Draw])])", "test_cost": 1, "test_correct": 0, "train_cost": 1, "train_correct": 0, "test_total": 1, "prune_count": 63}, {"complexity": 4, "task": 4, "trial": 1, "no._explored_programs": 1, "best_cost_per_iteration": [[0, 1]], "no._iterations": 5, "execution_time": 0.101587811, "best_program": "Program([LoopWhileThen(NotAtBottom [MoveDown], [Draw])])", "test_cost": 1, "test_correct": 0, "train_cost": 1, "train_correct": 0, "test_total": 1, "prune_count": 63}, {"complexity": 4, "task": 5, "trial": 1, "no._explored_programs": 1, "best_cost_per_iteration": [[0, 1]], "no._iterations": 5, "execution_time": 0.101475597, "best_program": "Program([LoopWhileThen(NotAtBottom [MoveDown], [Draw])])", "test_cost": 1, "test_correct": 0, "train_cost": 1, "train_correct": 0, "test_total": 1, "prune_count": 63}, {"complexity": 4, "task": 6, "trial": 1, "no._explored_programs": 1, "best_cost_per_iteration": [[0, 1]], "no._iterations": 5, "execution_time": 0.102152669, "best_program": "Program([LoopWhileThen(NotAtBottom [MoveDown], [Draw])])", "test_cost": 1, "test_correct": 0, "train_cost": 1, "train_correct": 0, "test_total": 1, "prune_count": 63}, {"complexity": 4, "task": 7, "trial": 1, "no._explored_programs": 1, "best_cost_per_iteration": [[0, 1]], "no._iterations": 5, "execution_time": 0.101748464, "best_program": "Program([LoopWhileThen(NotAtBottom [MoveDown], [Draw])])", "test_cost": 1, "test_correct": 0, "train_cost": 1, "train_correct": 0, "test_total": 1, "prune_count": 63}, {"complexity": 4, "task": 8, "trial": 1, "no._explored_programs": 1, "best_cost_per_iteration": [[0, 1]], "no._iterations": 5, "execution_time": 0.102327761, "best_program": "Program([LoopWhileThen(NotAtBottom [MoveDown], [Draw])])", "test_cost": 1, "test_correct": 0, "train_cost": 1, "train_correct": 0, "test_total": 1, "prune_count": 63}, {"complexity": 4, "task": 9, "trial": 1, "no._explored_programs": 1, "best_cost_per_iteration": [[0, 1]], "no._iterations": 5, "execution_time": 0.102459404, "best_program": "Program([LoopWhileThen(NotAtBottom [MoveDown], [Draw])])", "test_cost": 1, "test_correct": 0, "train_cost": 1, "train_correct": 0, "test_total": 1, "prune_count": 63}, {"complexity": 5, "task": 0, "trial": 1, "no._explored_programs": 1, "best_cost_per_iteration": [[0, 1]], "no._iterations": 5, "execution_time": 0.12169579300000002, "best_program": "Program([LoopWhileThen(NotAtBottom [MoveDown], [Draw])])", "test_cost": 1, "test_correct": 0, "train_cost": 1, "train_correct": 0, "test_total": 1, "prune_count": 63}, {"complexity": 5, "task": 1, "trial": 1, "no._explored_programs": 1, "best_cost_per_iteration": [[0, 1]], "no._iterations": 5, "execution_time": 0.12132400600000001, "best_program": "Program([LoopWhileThen(NotAtBottom [MoveDown], [Draw])])", "test_cost": 1, "test_correct": 0, "train_cost": 1, "train_correct": 0, "test_total": 1, "prune_count": 63}, {"complexity": 5, "task": 2, "trial": 1, "no._explored_programs": 1, "best_cost_per_iteration": [[0, 1]], "no._iterations": 5, "execution_time": 0.12341867699999999, "best_program": "Program([LoopWhileThen(NotAtBottom [MoveDown], [Draw])])", "test_cost": 1, "test_correct": 0, "train_cost": 1, "train_correct": 0, "test_total": 1, "prune_count": 63}, {"complexity": 5, "task": 3, "trial": 1, "no._explored_programs": 1, "best_cost_per_iteration": [[0, 1]], "no._iterations": 5, "execution_time": 0.12487739600000002, "best_program": "Program([LoopWhileThen(NotAtBottom [MoveDown], [Draw])])", "test_cost": 1, "test_correct": 0, "train_cost": 1, "train_correct": 0, "test_total": 1, "prune_count": 63}, {"complexity": 5, "task": 4, "trial": 1, "no._explored_programs": 1, "best_cost_per_iteration": [[0, 1]], "no._iterations": 5, "execution_time": 0.122780606, "best_program": "Program([LoopWhileThen(NotAtBottom [MoveDown], [Draw])])", "test_cost": 1, "test_correct": 0, "train_cost": 1, "train_correct": 0, "test_total": 1, "prune_count": 63}, {"complexity": 5, "task": 5, "trial": 1, "no._explored_programs": 1, "best_cost_per_iteration": [[0, 1]], "no._iterations": 5, "execution_time": 0.12306309100000001, "best_program": "Program([LoopWhileThen(NotAtBottom [MoveDown], [Draw])])", "test_cost": 1, "test_correct": 0, "train_cost": 1, "train_correct": 0, "test_total": 1, "prune_count": 63}, {"complexity": 5, "task": 6, "trial": 1, "no._explored_programs": 1, "best_cost_per_iteration": [[0, 1]], "no._iterations": 5, "execution_time": 0.12638124599999997, "best_program": "Program([LoopWhileThen(NotAtBottom [MoveDown], [Draw])])", "test_cost": 1, "test_correct": 0, "train_cost": 1, "train_correct": 0, "test_total": 1, "prune_count": 63}, {"complexity": 5, "task": 7, "trial": 1, "no._explored_programs": 1, "best_cost_per_iteration": [[0, 1]], "no._iterations": 5, "execution_time": 0.12084154599999997, "best_program": "Program([LoopWhileThen(NotAtBottom [MoveDown], [Draw])])", "test_cost": 1, "test_correct": 0, "train_cost": 1, "train_correct": 0, "test_total": 1, "prune_count": 63}, {"complexity": 5, "task": 8, "trial": 1, "no._explored_programs": 1, "best_cost_per_iteration": [[0, 1]], "no._iterations": 5, "execution_time": 0.12253467899999998, "best_program": "Program([LoopWhileThen(NotAtBottom [MoveDown], [Draw])])", "test_cost": 1, "test_correct": 0, "train_cost": 1, "train_correct": 0, "test_total": 1, "prune_count": 63}, {"complexity": 5, "task": 9, "trial": 1, "no._explored_programs": 1, "best_cost_per_iteration": [[0, 1]], "no._iterations": 5, "execution_time": 0.12227916100000003, "best_program": "Program([LoopWhileThen(NotAtBottom [MoveDown], [Draw])])", "test_cost": 1, "test_correct": 0, "train_cost": 1, "train_correct": 0, "test_total": 1, "prune_count": 63}]]